{
  "1": [
    {
      "順位": 1,
      "LR2ID": "63505",
      "プレイヤー": "生塩ノア",
      "スコア": "5093/5318(95.76%)",
      "PG": 2449,
      "GR": 195,
      "BPI": 57.39
    },
    {
      "順位": 2,
      "LR2ID": "140958",
      "プレイヤー": "浦和ハナコ",
      "スコア": "4984/5318(93.71%)",
      "PG": 2343,
      "GR": 298,
      "BPI": 37.03
    },
    {
      "順位": 3,
      "LR2ID": "166001",
      "プレイヤー": "しっちゅ",
      "スコア": "4929/5318(92.68%)",
      "PG": 2317,
      "GR": 295,
      "BPI": 28.43
    },
    {
      "順位": 4,
      "LR2ID": "116225",
      "プレイヤー": "各務チヒロ",
      "スコア": "4922/5318(92.55%)",
      "PG": 2286,
      "GR": 350,
      "BPI": 27.38
    },
    {
      "順位": 5,
      "LR2ID": "158558",
      "プレイヤー": "ののか福丼",
      "スコア": "4902/5318(92.17%)",
      "PG": 2275,
      "GR": 352,
      "BPI": 24.44
    },
    {
      "順位": 6,
      "LR2ID": "94429",
      "プレイヤー": "神谷奈緒",
      "スコア": "4864/5318(91.46%)",
      "PG": 2238,
      "GR": 388,
      "BPI": 18.97
    }
  ],
  "2": [
    {
      "順位": 1,
      "LR2ID": "63505",
      "プレイヤー": "生塩ノア",
      "スコア": "3937/3990(98.67%)",
      "PG": 1942,
      "GR": 53,
      "BPI": 63.11
    },
    {
      "順位": 2,
      "LR2ID": "166001",
      "プレイヤー": "しっちゅ",
      "スコア": "3928/3990(98.44%)",
      "PG": 1939,
      "GR": 50,
      "BPI": 58.19
    },
    {
      "順位": 3,
      "LR2ID": "116225",
      "プレイヤー": "各務チヒロ",
      "スコア": "3921/3990(98.27%)",
      "PG": 1933,
      "GR": 55,
      "BPI": 54.77
    },
    {
      "順位": 4,
      "LR2ID": "140958",
      "プレイヤー": "浦和ハナコ",
      "スコア": "3918/3990(98.19%)",
      "PG": 1926,
      "GR": 66,
      "BPI": 53.39
    },
    {
      "順位": 5,
      "LR2ID": "170023",
      "プレイヤー": "雪花ラミィ",
      "スコア": "3887/3990(97.41%)",
      "PG": 1899,
      "GR": 89,
      "BPI": 41.42
    },
    {
      "順位": 6,
      "LR2ID": "158558",
      "プレイヤー": "ののか福丼",
      "スコア": "3886/3990(97.39%)",
      "PG": 1896,
      "GR": 94,
      "BPI": 41.09
    },
    {
      "順位": 7,
      "LR2ID": "102160",
      "プレイヤー": "杏山カズサ",
      "スコア": "3659/3990(91.7%)",
      "PG": 1701,
      "GR": 257,
      "BPI": -15
    }
  ],
  "3": [
    {
      "順位": 1,
      "LR2ID": "63505",
      "プレイヤー": "生塩ノア",
      "スコア": "4796/4900(97.87%)",
      "PG": 2351,
      "GR": 94,
      "BPI": 60.08
    },
    {
      "順位": 2,
      "LR2ID": "140958",
      "プレイヤー": "浦和ハナコ",
      "スコア": "4638/4900(94.65%)",
      "PG": 2209,
      "GR": 220,
      "BPI": 23.05
    },
    {
      "順位": 3,
      "LR2ID": "166001",
      "プレイヤー": "しっちゅ",
      "スコア": "4485/4900(91.53%)",
      "PG": 2117,
      "GR": 251,
      "BPI": -15
    },
    {
      "順位": 4,
      "LR2ID": "116225",
      "プレイヤー": "各務チヒロ",
      "スコア": "4483/4900(91.48%)",
      "PG": 2118,
      "GR": 247,
      "BPI": -15
    },
    {
      "順位": 5,
      "LR2ID": "158558",
      "プレイヤー": "ののか福丼",
      "スコア": "4472/4900(91.26%)",
      "PG": 2071,
      "GR": 330,
      "BPI": -15
    }
  ],
  "4": [
    {
      "順位": 1,
      "LR2ID": "63505",
      "プレイヤー": "生塩ノア",
      "スコア": "4320/4350(99.31%)",
      "PG": 2146,
      "GR": 28,
      "BPI": 82.63
    },
    {
      "順位": 2,
      "LR2ID": "158558",
      "プレイヤー": "ののか福丼",
      "スコア": "4281/4350(98.41%)",
      "PG": 2117,
      "GR": 47,
      "BPI": 55.27
    },
    {
      "順位": 3,
      "LR2ID": "116225",
      "プレイヤー": "各務チヒロ",
      "スコア": "4234/4350(97.33%)",
      "PG": 2075,
      "GR": 84,
      "BPI": 36.37
    },
    {
      "順位": 4,
      "LR2ID": "140958",
      "プレイヤー": "浦和ハナコ",
      "スコア": "4233/4350(97.31%)",
      "PG": 2062,
      "GR": 109,
      "BPI": 36.04
    }
  ],
  "5": [
    {
      "順位": 1,
      "LR2ID": "63505",
      "プレイヤー": "生塩ノア",
      "スコア": "5708/5756(99.16%)",
      "PG": 2831,
      "GR": 46,
      "BPI": 92.58
    },
    {
      "順位": 2,
      "LR2ID": "116225",
      "プレイヤー": "各務チヒロ",
      "スコア": "5643/5756(98.03%)",
      "PG": 2784,
      "GR": 75,
      "BPI": 63.91
    },
    {
      "順位": 3,
      "LR2ID": "140958",
      "プレイヤー": "浦和ハナコ",
      "スコア": "5635/5756(97.89%)",
      "PG": 2765,
      "GR": 105,
      "BPI": 61.49
    },
    {
      "順位": 4,
      "LR2ID": "158558",
      "プレイヤー": "ののか福丼",
      "スコア": "5581/5756(96.95%)",
      "PG": 2721,
      "GR": 139,
      "BPI": 47.99
    },
    {
      "順位": 5,
      "LR2ID": "36363",
      "プレイヤー": "フリーナ",
      "スコア": "5554/5756(96.49%)",
      "PG": 2698,
      "GR": 158,
      "BPI": 42.49
    },
    {
      "順位": 6,
      "LR2ID": "170023",
      "プレイヤー": "雪花ラミィ",
      "スコア": "5506/5756(95.65%)",
      "PG": 2652,
      "GR": 202,
      "BPI": 33.96
    },
    {
      "順位": 7,
      "LR2ID": "102160",
      "プレイヤー": "杏山カズサ",
      "スコア": "5403/5756(93.86%)",
      "PG": 2570,
      "GR": 263,
      "BPI": 18.77
    },
    {
      "順位": 8,
      "LR2ID": "94429",
      "プレイヤー": "神谷奈緒",
      "スコア": "5390/5756(93.64%)",
      "PG": 2538,
      "GR": 314,
      "BPI": 17.02
    }
  ],
  "6": [
    {
      "順位": 1,
      "LR2ID": "63505",
      "プレイヤー": "生塩ノア",
      "スコア": "4507/4580(98.4%)",
      "PG": 2218,
      "GR": 71,
      "BPI": 70.7
    },
    {
      "順位": 2,
      "LR2ID": "166001",
      "プレイヤー": "しっちゅ",
      "スコア": "4421/4580(96.52%)",
      "PG": 2148,
      "GR": 125,
      "BPI": 39.83
    },
    {
      "順位": 3,
      "LR2ID": "140958",
      "プレイヤー": "浦和ハナコ",
      "スコア": "4420/4580(96.5%)",
      "PG": 2144,
      "GR": 132,
      "BPI": 39.56
    },
    {
      "順位": 4,
      "LR2ID": "102160",
      "プレイヤー": "杏山カズサ",
      "スコア": "4395/4580(95.96%)",
      "PG": 2118,
      "GR": 159,
      "BPI": 33.18
    },
    {
      "順位": 5,
      "LR2ID": "170023",
      "プレイヤー": "雪花ラミィ",
      "スコア": "4368/4580(95.37%)",
      "PG": 2097,
      "GR": 174,
      "BPI": 26.9
    },
    {
      "順位": 6,
      "LR2ID": "94429",
      "プレイヤー": "神谷奈緒",
      "スコア": "4346/4580(94.89%)",
      "PG": 2065,
      "GR": 216,
      "BPI": 22.11
    },
    {
      "順位": 7,
      "LR2ID": "116225",
      "プレイヤー": "各務チヒロ",
      "スコア": "4345/4580(94.86%)",
      "PG": 2087,
      "GR": 171,
      "BPI": 21.9
    },
    {
      "順位": 8,
      "LR2ID": "36363",
      "プレイヤー": "フリーナ",
      "スコア": "4302/4580(93.93%)",
      "PG": 2040,
      "GR": 222,
      "BPI": 13.01
    }
  ],
  "7": [
    {
      "順位": 1,
      "LR2ID": "174817",
      "プレイヤー": "マイマイ君",
      "スコア": "3200/3220(99.37%)",
      "PG": 1590,
      "GR": 20,
      "BPI": 81.84
    },
    {
      "順位": 2,
      "LR2ID": "63505",
      "プレイヤー": "生塩ノア",
      "スコア": "3197/3220(99.28%)",
      "PG": 1587,
      "GR": 23,
      "BPI": 77.45
    },
    {
      "順位": 3,
      "LR2ID": "166001",
      "プレイヤー": "しっちゅ",
      "スコア": "3188/3220(99%)",
      "PG": 1580,
      "GR": 28,
      "BPI": 66.83
    },
    {
      "順位": 4,
      "LR2ID": "170023",
      "プレイヤー": "雪花ラミィ",
      "スコア": "3166/3220(98.32%)",
      "PG": 1556,
      "GR": 54,
      "BPI": 49.03
    },
    {
      "順位": 5,
      "LR2ID": "158558",
      "プレイヤー": "ののか福丼",
      "スコア": "3164/3220(98.26%)",
      "PG": 1555,
      "GR": 54,
      "BPI": 47.73
    },
    {
      "順位": 6,
      "LR2ID": "116225",
      "プレイヤー": "各務チヒロ",
      "スコア": "3159/3220(98.1%)",
      "PG": 1556,
      "GR": 47,
      "BPI": 44.66
    },
    {
      "順位": 7,
      "LR2ID": "140958",
      "プレイヤー": "浦和ハナコ",
      "スコア": "3156/3220(98.01%)",
      "PG": 1548,
      "GR": 60,
      "BPI": 42.91
    },
    {
      "順位": 8,
      "LR2ID": "94429",
      "プレイヤー": "神谷奈緒",
      "スコア": "3153/3220(97.91%)",
      "PG": 1545,
      "GR": 63,
      "BPI": 41.22
    },
    {
      "順位": 9,
      "LR2ID": "36363",
      "プレイヤー": "フリーナ",
      "スコア": "3124/3220(97.01%)",
      "PG": 1518,
      "GR": 88,
      "BPI": 27.26
    },
    {
      "順位": 10,
      "LR2ID": "102160",
      "プレイヤー": "杏山カズサ",
      "スコア": "3117/3220(96.8%)",
      "PG": 1513,
      "GR": 91,
      "BPI": 24.33
    }
  ],
  "8": [
    {
      "順位": 1,
      "LR2ID": "63505",
      "プレイヤー": "生塩ノア",
      "スコア": "4036/4136(97.58%)",
      "PG": 1972,
      "GR": 92,
      "BPI": 77.58
    },
    {
      "順位": 2,
      "LR2ID": "174817",
      "プレイヤー": "マイマイ君",
      "スコア": "3990/4136(96.47%)",
      "PG": 1943,
      "GR": 104,
      "BPI": 62.03
    },
    {
      "順位": 3,
      "LR2ID": "140958",
      "プレイヤー": "浦和ハナコ",
      "スコア": "3954/4136(95.59%)",
      "PG": 1900,
      "GR": 154,
      "BPI": 52.53
    },
    {
      "順位": 4,
      "LR2ID": "166001",
      "プレイヤー": "しっちゅ",
      "スコア": "3913/4136(94.6%)",
      "PG": 1879,
      "GR": 155,
      "BPI": 43.36
    },
    {
      "順位": 5,
      "LR2ID": "158558",
      "プレイヤー": "ののか福丼",
      "スコア": "3903/4136(94.36%)",
      "PG": 1858,
      "GR": 187,
      "BPI": 41.32
    },
    {
      "順位": 6,
      "LR2ID": "170023",
      "プレイヤー": "雪花ラミィ",
      "スコア": "3869/4136(93.54%)",
      "PG": 1845,
      "GR": 179,
      "BPI": 34.81
    },
    {
      "順位": 7,
      "LR2ID": "94429",
      "プレイヤー": "神谷奈緒",
      "スコア": "3824/4136(92.45%)",
      "PG": 1802,
      "GR": 220,
      "BPI": 26.97
    },
    {
      "順位": 8,
      "LR2ID": "116225",
      "プレイヤー": "各務チヒロ",
      "スコア": "3784/4136(91.48%)",
      "PG": 1763,
      "GR": 258,
      "BPI": 20.48
    }
  ],
  "9": [
    {
      "順位": 1,
      "LR2ID": "63505",
      "プレイヤー": "生塩ノア",
      "スコア": "4503/4614(97.59%)",
      "PG": 2199,
      "GR": 105,
      "BPI": 50.1
    },
    {
      "順位": 2,
      "LR2ID": "174817",
      "プレイヤー": "マイマイ君",
      "スコア": "4497/4614(97.46%)",
      "PG": 2203,
      "GR": 91,
      "BPI": 48.2
    },
    {
      "順位": 3,
      "LR2ID": "166001",
      "プレイヤー": "しっちゅ",
      "スコア": "4467/4614(96.81%)",
      "PG": 2175,
      "GR": 117,
      "BPI": 39.73
    },
    {
      "順位": 4,
      "LR2ID": "116225",
      "プレイヤー": "各務チヒロ",
      "スコア": "4435/4614(96.12%)",
      "PG": 2146,
      "GR": 143,
      "BPI": 32.04
    },
    {
      "順位": 5,
      "LR2ID": "94429",
      "プレイヤー": "神谷奈緒",
      "スコア": "4433/4614(96.07%)",
      "PG": 2131,
      "GR": 171,
      "BPI": 31.59
    },
    {
      "順位": 6,
      "LR2ID": "158558",
      "プレイヤー": "ののか福丼",
      "スコア": "4428/4614(95.96%)",
      "PG": 2129,
      "GR": 170,
      "BPI": 30.49
    },
    {
      "順位": 7,
      "LR2ID": "36363",
      "プレイヤー": "フリーナ",
      "スコア": "4381/4614(94.95%)",
      "PG": 2090,
      "GR": 201,
      "BPI": 20.91
    },
    {
      "順位": 8,
      "LR2ID": "140958",
      "プレイヤー": "浦和ハナコ",
      "スコア": "4350/4614(94.27%)",
      "PG": 2053,
      "GR": 244,
      "BPI": 15.11
    },
    {
      "順位": 9,
      "LR2ID": "102160",
      "プレイヤー": "杏山カズサ",
      "スコア": "4280/4614(92.76%)",
      "PG": 2016,
      "GR": 248,
      "BPI": 1.53
    }
  ],
  "10": [
    {
      "順位": 1,
      "LR2ID": "63505",
      "プレイヤー": "生塩ノア",
      "スコア": "4039/4210(95.93%)",
      "PG": 1943,
      "GR": 153,
      "BPI": 50.57
    },
    {
      "順位": 2,
      "LR2ID": "174817",
      "プレイヤー": "マイマイ君",
      "スコア": "3971/4210(94.32%)",
      "PG": 1888,
      "GR": 195,
      "BPI": 33.74
    },
    {
      "順位": 3,
      "LR2ID": "94429",
      "プレイヤー": "神谷奈緒",
      "スコア": "3863/4210(91.75%)",
      "PG": 1776,
      "GR": 311,
      "BPI": 11.72
    },
    {
      "順位": 4,
      "LR2ID": "116225",
      "プレイヤー": "各務チヒロ",
      "スコア": "3807/4210(90.42%)",
      "PG": 1742,
      "GR": 323,
      "BPI": -15
    }
  ],
  "11": [
    {
      "順位": 1,
      "LR2ID": "63505",
      "プレイヤー": "生塩ノア",
      "スコア": "4170/4248(98.16%)",
      "PG": 2046,
      "GR": 78,
      "BPI": 72.98
    },
    {
      "順位": 2,
      "LR2ID": "174817",
      "プレイヤー": "マイマイ君",
      "スコア": "4138/4248(97.41%)",
      "PG": 2022,
      "GR": 94,
      "BPI": 59.68
    },
    {
      "順位": 3,
      "LR2ID": "158558",
      "プレイヤー": "ののか福丼",
      "スコア": "4077/4248(95.97%)",
      "PG": 1963,
      "GR": 151,
      "BPI": 41.4
    },
    {
      "順位": 4,
      "LR2ID": "166001",
      "プレイヤー": "しっちゅ",
      "スコア": "4036/4248(95%)",
      "PG": 1937,
      "GR": 162,
      "BPI": 31.75
    },
    {
      "順位": 5,
      "LR2ID": "116225",
      "プレイヤー": "各務チヒロ",
      "スコア": "3988/4248(93.87%)",
      "PG": 1876,
      "GR": 236,
      "BPI": 21.83
    },
    {
      "順位": 6,
      "LR2ID": "94429",
      "プレイヤー": "神谷奈緒",
      "スコア": "3981/4248(93.71%)",
      "PG": 1869,
      "GR": 243,
      "BPI": 20.46
    },
    {
      "順位": 7,
      "LR2ID": "140958",
      "プレイヤー": "浦和ハナコ",
      "スコア": "3979/4248(93.66%)",
      "PG": 1888,
      "GR": 203,
      "BPI": 20.08
    },
    {
      "順位": 8,
      "LR2ID": "102160",
      "プレイヤー": "杏山カズサ",
      "スコア": "3976/4248(93.59%)",
      "PG": 1881,
      "GR": 214,
      "BPI": 19.5
    },
    {
      "順位": 9,
      "LR2ID": "36363",
      "プレイヤー": "フリーナ",
      "スコア": "3962/4248(93.26%)",
      "PG": 1855,
      "GR": 252,
      "BPI": 16.81
    }
  ],
  "12": [
    {
      "順位": 1,
      "LR2ID": "63505",
      "プレイヤー": "生塩ノア",
      "スコア": "3617/3630(99.64%)",
      "PG": 1802,
      "GR": 13,
      "BPI": 83.05
    },
    {
      "順位": 2,
      "LR2ID": "174817",
      "プレイヤー": "マイマイ君",
      "スコア": "3610/3630(99.44%)",
      "PG": 1795,
      "GR": 20,
      "BPI": 70.74
    },
    {
      "順位": 2,
      "LR2ID": "166001",
      "プレイヤー": "しっちゅ",
      "スコア": "3610/3630(99.44%)",
      "PG": 1796,
      "GR": 18,
      "BPI": 70.74
    },
    {
      "順位": 4,
      "LR2ID": "170023",
      "プレイヤー": "雪花ラミィ",
      "スコア": "3579/3630(98.59%)",
      "PG": 1769,
      "GR": 41,
      "BPI": 41.74
    },
    {
      "順位": 5,
      "LR2ID": "158558",
      "プレイヤー": "ののか福丼",
      "スコア": "3567/3630(98.26%)",
      "PG": 1754,
      "GR": 59,
      "BPI": 34.54
    },
    {
      "順位": 6,
      "LR2ID": "36363",
      "プレイヤー": "フリーナ",
      "スコア": "3561/3630(98.09%)",
      "PG": 1746,
      "GR": 69,
      "BPI": 31.32
    },
    {
      "順位": 7,
      "LR2ID": "116225",
      "プレイヤー": "各務チヒロ",
      "スコア": "3560/3630(98.07%)",
      "PG": 1748,
      "GR": 64,
      "BPI": 30.81
    },
    {
      "順位": 8,
      "LR2ID": "94429",
      "プレイヤー": "神谷奈緒",
      "スコア": "3538/3630(97.46%)",
      "PG": 1729,
      "GR": 80,
      "BPI": 20.52
    }
  ],
  "13": [
    {
      "順位": 1,
      "LR2ID": "166001",
      "プレイヤー": "しっちゅ",
      "スコア": "3366/3628(92.77%)",
      "PG": 1609,
      "GR": 148,
      "BPI": 35.1
    },
    {
      "順位": 2,
      "LR2ID": "158558",
      "プレイヤー": "ののか福丼",
      "スコア": "3357/3628(92.53%)",
      "PG": 1589,
      "GR": 179,
      "BPI": 33.19
    },
    {
      "順位": 3,
      "LR2ID": "140958",
      "プレイヤー": "浦和ハナコ",
      "スコア": "3303/3628(91.04%)",
      "PG": 1529,
      "GR": 245,
      "BPI": 22.34
    },
    {
      "順位": 4,
      "LR2ID": "170023",
      "プレイヤー": "雪花ラミィ",
      "スコア": "3285/3628(90.54%)",
      "PG": 1542,
      "GR": 201,
      "BPI": 18.87
    },
    {
      "順位": 5,
      "LR2ID": "36363",
      "プレイヤー": "フリーナ",
      "スコア": "3254/3628(89.69%)",
      "PG": 1496,
      "GR": 262,
      "BPI": 12.94
    },
    {
      "順位": 6,
      "LR2ID": "63505",
      "プレイヤー": "生塩ノア",
      "スコア": "3238/3628(89.25%)",
      "PG": 1474,
      "GR": 290,
      "BPI": 9.81
    },
    {
      "順位": 7,
      "LR2ID": "116225",
      "プレイヤー": "各務チヒロ",
      "スコア": "3207/3628(88.39%)",
      "PG": 1468,
      "GR": 271,
      "BPI": 3.2
    },
    {
      "順位": 8,
      "LR2ID": "94429",
      "プレイヤー": "神谷奈緒",
      "スコア": "3127/3628(86.19%)",
      "PG": 1403,
      "GR": 321,
      "BPI": -15
    }
  ],
  "14": [
    {
      "順位": 1,
      "LR2ID": "166001",
      "プレイヤー": "しっちゅ",
      "スコア": "3807/4012(94.89%)",
      "PG": 1845,
      "GR": 117,
      "BPI": 60.67
    },
    {
      "順位": 2,
      "LR2ID": "140958",
      "プレイヤー": "浦和ハナコ",
      "スコア": "3778/4012(94.16%)",
      "PG": 1810,
      "GR": 158,
      "BPI": 53.21
    },
    {
      "順位": 3,
      "LR2ID": "174817",
      "プレイヤー": "マイマイ君",
      "スコア": "3774/4012(94.06%)",
      "PG": 1822,
      "GR": 130,
      "BPI": 52.24
    },
    {
      "順位": 4,
      "LR2ID": "158558",
      "プレイヤー": "ののか福丼",
      "スコア": "3772/4012(94.01%)",
      "PG": 1805,
      "GR": 162,
      "BPI": 51.75
    },
    {
      "順位": 5,
      "LR2ID": "170023",
      "プレイヤー": "雪花ラミィ",
      "スコア": "3725/4012(92.84%)",
      "PG": 1760,
      "GR": 205,
      "BPI": 41.14
    },
    {
      "順位": 6,
      "LR2ID": "116225",
      "プレイヤー": "各務チヒロ",
      "スコア": "3718/4012(92.67%)",
      "PG": 1759,
      "GR": 200,
      "BPI": 39.66
    },
    {
      "順位": 7,
      "LR2ID": "102160",
      "プレイヤー": "杏山カズサ",
      "スコア": "3690/4012(91.97%)",
      "PG": 1742,
      "GR": 206,
      "BPI": 33.93
    },
    {
      "順位": 8,
      "LR2ID": "94429",
      "プレイヤー": "神谷奈緒",
      "スコア": "3615/4012(90.1%)",
      "PG": 1667,
      "GR": 281,
      "BPI": 19.64
    },
    {
      "順位": 9,
      "LR2ID": "36363",
      "プレイヤー": "フリーナ",
      "スコア": "3601/4012(89.75%)",
      "PG": 1653,
      "GR": 295,
      "BPI": 17.05
    },
    {
      "順位": 10,
      "LR2ID": "63505",
      "プレイヤー": "生塩ノア",
      "スコア": "3593/4012(89.55%)",
      "PG": 1662,
      "GR": 269,
      "BPI": 15.56
    }
  ],
  "15": [
    {
      "順位": 1,
      "LR2ID": "63505",
      "プレイヤー": "生塩ノア",
      "スコア": "4340/4346(99.86%)",
      "PG": 2167,
      "GR": 6,
      "BPI": 61.57
    },
    {
      "順位": 2,
      "LR2ID": "116225",
      "プレイヤー": "各務チヒロ",
      "スコア": "4330/4346(99.63%)",
      "PG": 2157,
      "GR": 16,
      "BPI": 44.75
    },
    {
      "順位": 3,
      "LR2ID": "36363",
      "プレイヤー": "フリーナ",
      "スコア": "4328/4346(99.58%)",
      "PG": 2157,
      "GR": 14,
      "BPI": 42.63
    },
    {
      "順位": 4,
      "LR2ID": "102160",
      "プレイヤー": "杏山カズサ",
      "スコア": "4318/4346(99.35%)",
      "PG": 2153,
      "GR": 12,
      "BPI": 34.42
    },
    {
      "順位": 5,
      "LR2ID": "140958",
      "プレイヤー": "浦和ハナコ",
      "スコア": "4304/4346(99.03%)",
      "PG": 2136,
      "GR": 32,
      "BPI": 26.43
    },
    {
      "順位": 6,
      "LR2ID": "94429",
      "プレイヤー": "神谷奈緒",
      "スコア": "4301/4346(98.96%)",
      "PG": 2131,
      "GR": 39,
      "BPI": 25.01
    },
    {
      "順位": 7,
      "LR2ID": "170023",
      "プレイヤー": "雪花ラミィ",
      "スコア": "1769/4346(40.7%)",
      "PG": 876,
      "GR": 17,
      "BPI": -15
    }
  ],
  "16": [
    {
      "順位": 1,
      "LR2ID": "63505",
      "プレイヤー": "生塩ノア",
      "スコア": "3799/3898(97.46%)",
      "PG": 1859,
      "GR": 81,
      "BPI": 76.06
    },
    {
      "順位": 2,
      "LR2ID": "170023",
      "プレイヤー": "雪花ラミィ",
      "スコア": "3712/3898(95.22%)",
      "PG": 1783,
      "GR": 146,
      "BPI": 48.0
    },
    {
      "順位": 3,
      "LR2ID": "158558",
      "プレイヤー": "ののか福丼",
      "スコア": "3700/3898(94.92%)",
      "PG": 1777,
      "GR": 146,
      "BPI": 45.02
    },
    {
      "順位": 4,
      "LR2ID": "140958",
      "プレイヤー": "浦和ハナコ",
      "スコア": "3689/3898(94.63%)",
      "PG": 1755,
      "GR": 179,
      "BPI": 42.39
    },
    {
      "順位": 5,
      "LR2ID": "116225",
      "プレイヤー": "各務チヒロ",
      "スコア": "3687/3898(94.58%)",
      "PG": 1761,
      "GR": 165,
      "BPI": 41.93
    },
    {
      "順位": 6,
      "LR2ID": "36363",
      "プレイヤー": "フリーナ",
      "スコア": "3671/3898(94.17%)",
      "PG": 1738,
      "GR": 195,
      "BPI": 38.31
    },
    {
      "順位": 7,
      "LR2ID": "94429",
      "プレイヤー": "神谷奈緒",
      "スコア": "3656/3898(93.79%)",
      "PG": 1726,
      "GR": 204,
      "BPI": 35.07
    },
    {
      "順位": 8,
      "LR2ID": "102160",
      "プレイヤー": "杏山カズサ",
      "スコア": "3583/3898(91.91%)",
      "PG": 1680,
      "GR": 223,
      "BPI": 20.73
    }
  ],
  "17": [
    {
      "順位": 1,
      "LR2ID": "63505",
      "プレイヤー": "生塩ノア",
      "スコア": "4445/4514(98.47%)",
      "PG": 2190,
      "GR": 65,
      "BPI": 56.29
    },
    {
      "順位": 2,
      "LR2ID": "102160",
      "プレイヤー": "杏山カズサ",
      "スコア": "4364/4514(96.67%)",
      "PG": 2123,
      "GR": 118,
      "BPI": 32.9
    },
    {
      "順位": 3,
      "LR2ID": "158558",
      "プレイヤー": "ののか福丼",
      "スコア": "4363/4514(96.65%)",
      "PG": 2114,
      "GR": 135,
      "BPI": 32.68
    },
    {
      "順位": 4,
      "LR2ID": "116225",
      "プレイヤー": "各務チヒロ",
      "スコア": "4337/4514(96.07%)",
      "PG": 2095,
      "GR": 147,
      "BPI": 27.41
    },
    {
      "順位": 5,
      "LR2ID": "140958",
      "プレイヤー": "浦和ハナコ",
      "スコア": "4324/4514(95.79%)",
      "PG": 2078,
      "GR": 168,
      "BPI": 24.98
    },
    {
      "順位": 6,
      "LR2ID": "36363",
      "プレイヤー": "フリーナ",
      "スコア": "4297/4514(95.19%)",
      "PG": 2050,
      "GR": 197,
      "BPI": 20.25
    },
    {
      "順位": 7,
      "LR2ID": "170023",
      "プレイヤー": "雪花ラミィ",
      "スコア": "4289/4514(95.01%)",
      "PG": 2044,
      "GR": 201,
      "BPI": 18.91
    },
    {
      "順位": 8,
      "LR2ID": "94429",
      "プレイヤー": "神谷奈緒",
      "スコア": "4273/4514(94.66%)",
      "PG": 2041,
      "GR": 191,
      "BPI": 16.3
    }
  ],
  "18": [
    {
      "順位": 1,
      "LR2ID": "63505",
      "プレイヤー": "生塩ノア",
      "スコア": "4060/4096(99.12%)",
      "PG": 2014,
      "GR": 32,
      "BPI": 68.49
    },
    {
      "順位": 2,
      "LR2ID": "166001",
      "プレイヤー": "しっちゅ",
      "スコア": "4049/4096(98.85%)",
      "PG": 2004,
      "GR": 41,
      "BPI": 58.19
    },
    {
      "順位": 3,
      "LR2ID": "140958",
      "プレイヤー": "浦和ハナコ",
      "スコア": "4020/4096(98.14%)",
      "PG": 1972,
      "GR": 76,
      "BPI": 38.31
    },
    {
      "順位": 4,
      "LR2ID": "170023",
      "プレイヤー": "雪花ラミィ",
      "スコア": "4014/4096(97.99%)",
      "PG": 1969,
      "GR": 76,
      "BPI": 34.94
    },
    {
      "順位": 4,
      "LR2ID": "94429",
      "プレイヤー": "神谷奈緒",
      "スコア": "4014/4096(97.99%)",
      "PG": 1967,
      "GR": 80,
      "BPI": 34.94
    },
    {
      "順位": 6,
      "LR2ID": "116225",
      "プレイヤー": "各務チヒロ",
      "スコア": "4011/4096(97.92%)",
      "PG": 1967,
      "GR": 77,
      "BPI": 33.32
    },
    {
      "順位": 7,
      "LR2ID": "36363",
      "プレイヤー": "フリーナ",
      "スコア": "3993/4096(97.48%)",
      "PG": 1946,
      "GR": 101,
      "BPI": 24.29
    }
  ],
  "19": [
    {
      "順位": 1,
      "LR2ID": "63505",
      "プレイヤー": "生塩ノア",
      "スコア": "4192/4242(98.82%)",
      "PG": 2072,
      "GR": 48,
      "BPI": 60.22
    },
    {
      "順位": 2,
      "LR2ID": "158558",
      "プレイヤー": "ののか福丼",
      "スコア": "4186/4242(98.67%)",
      "PG": 2072,
      "GR": 42,
      "BPI": 56.39
    },
    {
      "順位": 3,
      "LR2ID": "184466",
      "プレイヤー": "なんこつ君",
      "スコア": "4156/4242(97.97%)",
      "PG": 2043,
      "GR": 70,
      "BPI": 41.24
    },
    {
      "順位": 4,
      "LR2ID": "116225",
      "プレイヤー": "各務チヒロ",
      "スコア": "4154/4242(97.92%)",
      "PG": 2046,
      "GR": 62,
      "BPI": 40.39
    },
    {
      "順位": 5,
      "LR2ID": "170023",
      "プレイヤー": "雪花ラミィ",
      "スコア": "4144/4242(97.68%)",
      "PG": 2031,
      "GR": 82,
      "BPI": 36.35
    },
    {
      "順位": 6,
      "LR2ID": "140958",
      "プレイヤー": "浦和ハナコ",
      "スコア": "4129/4242(97.33%)",
      "PG": 2019,
      "GR": 91,
      "BPI": 30.83
    },
    {
      "順位": 7,
      "LR2ID": "36363",
      "プレイヤー": "フリーナ",
      "スコア": "4126/4242(97.26%)",
      "PG": 2018,
      "GR": 90,
      "BPI": 29.79
    },
    {
      "順位": 8,
      "LR2ID": "102160",
      "プレイヤー": "杏山カズサ",
      "スコア": "4067/4242(95.87%)",
      "PG": 1969,
      "GR": 129,
      "BPI": 11.7
    }
  ],
  "20": [
    {
      "順位": 1,
      "LR2ID": "63505",
      "プレイヤー": "生塩ノア",
      "スコア": "3514/3538(99.32%)",
      "PG": 1746,
      "GR": 22,
      "BPI": 89.05
    },
    {
      "順位": 2,
      "LR2ID": "174817",
      "プレイヤー": "マイマイ君",
      "スコア": "3502/3538(98.98%)",
      "PG": 1737,
      "GR": 28,
      "BPI": 75.73
    },
    {
      "順位": 3,
      "LR2ID": "140958",
      "プレイヤー": "浦和ハナコ",
      "スコア": "3474/3538(98.19%)",
      "PG": 1706,
      "GR": 62,
      "BPI": 55.72
    },
    {
      "順位": 4,
      "LR2ID": "102160",
      "プレイヤー": "杏山カズサ",
      "スコア": "3455/3538(97.65%)",
      "PG": 1693,
      "GR": 69,
      "BPI": 46.08
    },
    {
      "順位": 5,
      "LR2ID": "170023",
      "プレイヤー": "雪花ラミィ",
      "スコア": "3454/3538(97.62%)",
      "PG": 1695,
      "GR": 64,
      "BPI": 45.63
    },
    {
      "順位": 6,
      "LR2ID": "94429",
      "プレイヤー": "神谷奈緒",
      "スコア": "3442/3538(97.28%)",
      "PG": 1677,
      "GR": 88,
      "BPI": 40.47
    },
    {
      "順位": 7,
      "LR2ID": "116225",
      "プレイヤー": "各務チヒロ",
      "スコア": "3434/3538(97.06%)",
      "PG": 1671,
      "GR": 92,
      "BPI": 37.29
    },
    {
      "順位": 8,
      "LR2ID": "36363",
      "プレイヤー": "フリーナ",
      "スコア": "3391/3538(95.84%)",
      "PG": 1636,
      "GR": 119,
      "BPI": 22.63
    },
    {
      "順位": 9,
      "LR2ID": "183732",
      "プレイヤー": "kirsiKB",
      "スコア": "3254/3538(91.97%)",
      "PG": 1527,
      "GR": 200,
      "BPI": -15
    }
  ],
  "21": [
    {
      "順位": 1,
      "LR2ID": "174817",
      "プレイヤー": "マイマイ君",
      "スコア": "3766/3788(99.41%)",
      "PG": 1872,
      "GR": 22,
      "BPI": 83.96
    },
    {
      "順位": 2,
      "LR2ID": "63505",
      "プレイヤー": "生塩ノア",
      "スコア": "3764/3788(99.36%)",
      "PG": 1870,
      "GR": 24,
      "BPI": 81.24
    },
    {
      "順位": 3,
      "LR2ID": "170023",
      "プレイヤー": "雪花ラミィ",
      "スコア": "3739/3788(98.7%)",
      "PG": 1848,
      "GR": 43,
      "BPI": 57.89
    },
    {
      "順位": 4,
      "LR2ID": "140958",
      "プレイヤー": "浦和ハナコ",
      "スコア": "3727/3788(98.38%)",
      "PG": 1836,
      "GR": 55,
      "BPI": 50.26
    },
    {
      "順位": 5,
      "LR2ID": "94429",
      "プレイヤー": "神谷奈緒",
      "スコア": "3706/3788(97.83%)",
      "PG": 1817,
      "GR": 72,
      "BPI": 39.47
    },
    {
      "順位": 6,
      "LR2ID": "116225",
      "プレイヤー": "各務チヒロ",
      "スコア": "3704/3788(97.78%)",
      "PG": 1814,
      "GR": 76,
      "BPI": 38.56
    },
    {
      "順位": 7,
      "LR2ID": "36363",
      "プレイヤー": "フリーナ",
      "スコア": "3701/3788(97.7%)",
      "PG": 1811,
      "GR": 79,
      "BPI": 37.22
    }
  ],
  "22": [
    {
      "順位": 1,
      "LR2ID": "63505",
      "プレイヤー": "生塩ノア",
      "スコア": "5792/5850(99%)",
      "PG": 2868,
      "GR": 56,
      "BPI": 61.31
    },
    {
      "順位": 2,
      "LR2ID": "174817",
      "プレイヤー": "マイマイ君",
      "スコア": "5734/5850(98.01%)",
      "PG": 2821,
      "GR": 92,
      "BPI": 43.35
    },
    {
      "順位": 3,
      "LR2ID": "140958",
      "プレイヤー": "浦和ハナコ",
      "スコア": "5721/5850(97.79%)",
      "PG": 2804,
      "GR": 113,
      "BPI": 40.45
    },
    {
      "順位": 4,
      "LR2ID": "184466",
      "プレイヤー": "なんこつ君",
      "スコア": "5688/5850(97.23%)",
      "PG": 2775,
      "GR": 138,
      "BPI": 34.02
    },
    {
      "順位": 5,
      "LR2ID": "170023",
      "プレイヤー": "雪花ラミィ",
      "スコア": "5618/5850(96.03%)",
      "PG": 2722,
      "GR": 174,
      "BPI": 23.2
    },
    {
      "順位": 6,
      "LR2ID": "94429",
      "プレイヤー": "神谷奈緒",
      "スコア": "5580/5850(95.38%)",
      "PG": 2661,
      "GR": 258,
      "BPI": 18.25
    },
    {
      "順位": 7,
      "LR2ID": "36363",
      "プレイヤー": "フリーナ",
      "スコア": "5569/5850(95.19%)",
      "PG": 2656,
      "GR": 257,
      "BPI": 16.89
    },
    {
      "順位": 8,
      "LR2ID": "102160",
      "プレイヤー": "杏山カズサ",
      "スコア": "5477/5850(93.62%)",
      "PG": 2583,
      "GR": 311,
      "BPI": 6.11
    },
    {
      "順位": 9,
      "LR2ID": "116225",
      "プレイヤー": "各務チヒロ",
      "スコア": "5473/5850(93.55%)",
      "PG": 2586,
      "GR": 301,
      "BPI": 5.63
    }
  ],
  "23": [
    {
      "順位": 1,
      "LR2ID": "63505",
      "プレイヤー": "生塩ノア",
      "スコア": "4426/4444(99.59%)",
      "PG": 2204,
      "GR": 18,
      "BPI": 85.14
    },
    {
      "順位": 2,
      "LR2ID": "184466",
      "プレイヤー": "なんこつ君",
      "スコア": "4420/4444(99.45%)",
      "PG": 2199,
      "GR": 22,
      "BPI": 77.63
    },
    {
      "順位": 3,
      "LR2ID": "158558",
      "プレイヤー": "ののか福丼",
      "スコア": "4401/4444(99.03%)",
      "PG": 2181,
      "GR": 39,
      "BPI": 61.81
    },
    {
      "順位": 4,
      "LR2ID": "116225",
      "プレイヤー": "各務チヒロ",
      "スコア": "4384/4444(98.64%)",
      "PG": 2169,
      "GR": 46,
      "BPI": 52.3
    },
    {
      "順位": 5,
      "LR2ID": "140958",
      "プレイヤー": "浦和ハナコ",
      "スコア": "4362/4444(98.15%)",
      "PG": 2143,
      "GR": 76,
      "BPI": 42.98
    },
    {
      "順位": 6,
      "LR2ID": "36363",
      "プレイヤー": "フリーナ",
      "スコア": "4359/4444(98.08%)",
      "PG": 2145,
      "GR": 69,
      "BPI": 41.88
    },
    {
      "順位": 7,
      "LR2ID": "170023",
      "プレイヤー": "雪花ラミィ",
      "スコア": "4358/4444(98.06%)",
      "PG": 2142,
      "GR": 74,
      "BPI": 41.52
    },
    {
      "順位": 8,
      "LR2ID": "94429",
      "プレイヤー": "神谷奈緒",
      "スコア": "4331/4444(97.45%)",
      "PG": 2118,
      "GR": 95,
      "BPI": 32.84
    },
    {
      "順位": 9,
      "LR2ID": "102160",
      "プレイヤー": "杏山カズサ",
      "スコア": "4201/4444(94.53%)",
      "PG": 1997,
      "GR": 207,
      "BPI": 2.79
    }
  ],
  "24": [
    {
      "順位": 1,
      "LR2ID": "63505",
      "プレイヤー": "生塩ノア",
      "スコア": "4977/5000(99.54%)",
      "PG": 2477,
      "GR": 23,
      "BPI": 81.08
    },
    {
      "順位": 2,
      "LR2ID": "187038",
      "プレイヤー": "PanPiano",
      "スコア": "4950/5000(99%)",
      "PG": 2456,
      "GR": 38,
      "BPI": 59.86
    },
    {
      "順位": 3,
      "LR2ID": "184466",
      "プレイヤー": "なんこつ君",
      "スコア": "4947/5000(98.94%)",
      "PG": 2452,
      "GR": 43,
      "BPI": 58.2
    },
    {
      "順位": 4,
      "LR2ID": "140958",
      "プレイヤー": "浦和ハナコ",
      "スコア": "4946/5000(98.92%)",
      "PG": 2447,
      "GR": 52,
      "BPI": 57.66
    },
    {
      "順位": 5,
      "LR2ID": "158558",
      "プレイヤー": "ののか福丼",
      "スコア": "4944/5000(98.88%)",
      "PG": 2452,
      "GR": 40,
      "BPI": 56.62
    },
    {
      "順位": 6,
      "LR2ID": "116225",
      "プレイヤー": "各務チヒロ",
      "スコア": "4929/5000(98.58%)",
      "PG": 2440,
      "GR": 49,
      "BPI": 49.66
    },
    {
      "順位": 7,
      "LR2ID": "36363",
      "プレイヤー": "フリーナ",
      "スコア": "4913/5000(98.26%)",
      "PG": 2420,
      "GR": 73,
      "BPI": 43.51
    },
    {
      "順位": 8,
      "LR2ID": "94429",
      "プレイヤー": "神谷奈緒",
      "スコア": "4799/5000(95.98%)",
      "PG": 2311,
      "GR": 177,
      "BPI": 14.76
    }
  ],
  "25": [
    {
      "順位": 1,
      "LR2ID": "187038",
      "プレイヤー": "PanPiano",
      "スコア": "5967/6000(99.45%)",
      "PG": 2969,
      "GR": 29,
      "BPI": 71.79
    },
    {
      "順位": 2,
      "LR2ID": "63505",
      "プレイヤー": "生塩ノア",
      "スコア": "5961/6000(99.35%)",
      "PG": 2961,
      "GR": 39,
      "BPI": 67.28
    },
    {
      "順位": 3,
      "LR2ID": "184466",
      "プレイヤー": "なんこつ君",
      "スコア": "5897/6000(98.28%)",
      "PG": 2913,
      "GR": 71,
      "BPI": 39.13
    },
    {
      "順位": 4,
      "LR2ID": "158558",
      "プレイヤー": "ののか福丼",
      "スコア": "5871/6000(97.85%)",
      "PG": 2884,
      "GR": 103,
      "BPI": 31.93
    },
    {
      "順位": 5,
      "LR2ID": "170023",
      "プレイヤー": "雪花ラミィ",
      "スコア": "5869/6000(97.81%)",
      "PG": 2877,
      "GR": 115,
      "BPI": 31.42
    },
    {
      "順位": 6,
      "LR2ID": "140958",
      "プレイヤー": "浦和ハナコ",
      "スコア": "5848/6000(97.46%)",
      "PG": 2865,
      "GR": 118,
      "BPI": 26.42
    },
    {
      "順位": 7,
      "LR2ID": "102160",
      "プレイヤー": "杏山カズサ",
      "スコア": "5840/6000(97.33%)",
      "PG": 2845,
      "GR": 150,
      "BPI": 24.63
    },
    {
      "順位": 8,
      "LR2ID": "116225",
      "プレイヤー": "各務チヒロ",
      "スコア": "5838/6000(97.3%)",
      "PG": 2862,
      "GR": 114,
      "BPI": 24.2
    },
    {
      "順位": 9,
      "LR2ID": "36363",
      "プレイヤー": "フリーナ",
      "スコア": "5813/6000(96.88%)",
      "PG": 2836,
      "GR": 141,
      "BPI": 19.0
    },
    {
      "順位": 10,
      "LR2ID": "94429",
      "プレイヤー": "神谷奈緒",
      "スコア": "5758/6000(95.96%)",
      "PG": 2792,
      "GR": 174,
      "BPI": 8.49
    }
  ],
  "26": [
    {
      "順位": 1,
      "LR2ID": "187038",
      "プレイヤー": "PanPiano",
      "スコア": "3281/3300(99.42%)",
      "PG": 1632,
      "GR": 17,
      "BPI": 59.03
    },
    {
      "順位": 2,
      "LR2ID": "63505",
      "プレイヤー": "生塩ノア",
      "スコア": "3273/3300(99.18%)",
      "PG": 1624,
      "GR": 25,
      "BPI": 50.48
    },
    {
      "順位": 3,
      "LR2ID": "184466",
      "プレイヤー": "なんこつ君",
      "スコア": "3269/3300(99.06%)",
      "PG": 1620,
      "GR": 29,
      "BPI": 47.02
    },
    {
      "順位": 4,
      "LR2ID": "105437",
      "プレイヤー": "comet*",
      "スコア": "3260/3300(98.78%)",
      "PG": 1611,
      "GR": 38,
      "BPI": 40.47
    },
    {
      "順位": 5,
      "LR2ID": "158558",
      "プレイヤー": "ののか福丼",
      "スコア": "3259/3300(98.75%)",
      "PG": 1610,
      "GR": 39,
      "BPI": 39.82
    },
    {
      "順位": 6,
      "LR2ID": "36363",
      "プレイヤー": "フリーナ",
      "スコア": "3253/3300(98.57%)",
      "PG": 1605,
      "GR": 43,
      "BPI": 36.18
    },
    {
      "順位": 7,
      "LR2ID": "116225",
      "プレイヤー": "各務チヒロ",
      "スコア": "3243/3300(98.27%)",
      "PG": 1600,
      "GR": 43,
      "BPI": 30.88
    },
    {
      "順位": 8,
      "LR2ID": "140958",
      "プレイヤー": "浦和ハナコ",
      "スコア": "3240/3300(98.18%)",
      "PG": 1590,
      "GR": 60,
      "BPI": 29.43
    },
    {
      "順位": 9,
      "LR2ID": "170023",
      "プレイヤー": "雪花ラミィ",
      "スコア": "3235/3300(98.03%)",
      "PG": 1586,
      "GR": 63,
      "BPI": 27.13
    },
    {
      "順位": 10,
      "LR2ID": "94429",
      "プレイヤー": "神谷奈緒",
      "スコア": "3193/3300(96.75%)",
      "PG": 1547,
      "GR": 99,
      "BPI": 11.3
    }
  ],
  "27": [
    {
      "順位": 1,
      "LR2ID": "187038",
      "プレイヤー": "PanPiano",
      "スコア": "3816/3856(98.96%)",
      "PG": 1889,
      "GR": 38,
      "BPI": 88.17
    },
    {
      "順位": 2,
      "LR2ID": "63505",
      "プレイヤー": "生塩ノア",
      "スコア": "3801/3856(98.57%)",
      "PG": 1876,
      "GR": 49,
      "BPI": 77.25
    },
    {
      "順位": 3,
      "LR2ID": "101654",
      "プレイヤー": "ウドフル君",
      "スコア": "3765/3856(97.64%)",
      "PG": 1844,
      "GR": 77,
      "BPI": 59.14
    },
    {
      "順位": 4,
      "LR2ID": "105437",
      "プレイヤー": "comet*",
      "スコア": "3749/3856(97.22%)",
      "PG": 1829,
      "GR": 91,
      "BPI": 53.02
    },
    {
      "順位": 5,
      "LR2ID": "158558",
      "プレイヤー": "ののか福丼",
      "スコア": "3736/3856(96.88%)",
      "PG": 1819,
      "GR": 98,
      "BPI": 48.58
    },
    {
      "順位": 6,
      "LR2ID": "140958",
      "プレイヤー": "浦和ハナコ",
      "スコア": "3728/3856(96.68%)",
      "PG": 1808,
      "GR": 112,
      "BPI": 46.04
    },
    {
      "順位": 7,
      "LR2ID": "170023",
      "プレイヤー": "雪花ラミィ",
      "スコア": "3715/3856(96.34%)",
      "PG": 1805,
      "GR": 105,
      "BPI": 42.16
    },
    {
      "順位": 8,
      "LR2ID": "184466",
      "プレイヤー": "なんこつ君",
      "スコア": "3700/3856(95.95%)",
      "PG": 1796,
      "GR": 108,
      "BPI": 38.01
    },
    {
      "順位": 9,
      "LR2ID": "36363",
      "プレイヤー": "フリーナ",
      "スコア": "3680/3856(95.43%)",
      "PG": 1774,
      "GR": 132,
      "BPI": 32.9
    },
    {
      "順位": 10,
      "LR2ID": "116225",
      "プレイヤー": "各務チヒロ",
      "スコア": "3644/3856(94.5%)",
      "PG": 1760,
      "GR": 124,
      "BPI": 24.59
    },
    {
      "順位": 11,
      "LR2ID": "94429",
      "プレイヤー": "神谷奈緒",
      "スコア": "3631/3856(94.16%)",
      "PG": 1726,
      "GR": 179,
      "BPI": 21.79
    },
    {
      "順位": 12,
      "LR2ID": "102160",
      "プレイヤー": "杏山カズサ",
      "スコア": "3626/3856(94.03%)",
      "PG": 1719,
      "GR": 188,
      "BPI": 20.73
    }
  ],
  "28": [
    {
      "順位": 1,
      "LR2ID": "101654",
      "プレイヤー": "ウドフル君",
      "スコア": "4294/4300(99.86%)",
      "PG": 2144,
      "GR": 6,
      "BPI": 100.0
    },
    {
      "順位": 2,
      "LR2ID": "187038",
      "プレイヤー": "PanPiano",
      "スコア": "4293/4300(99.83%)",
      "PG": 2143,
      "GR": 7,
      "BPI": 96.35
    },
    {
      "順位": 3,
      "LR2ID": "63505",
      "プレイヤー": "生塩ノア",
      "スコア": "4290/4300(99.76%)",
      "PG": 2140,
      "GR": 10,
      "BPI": 87.76
    },
    {
      "順位": 4,
      "LR2ID": "166001",
      "プレイヤー": "しっちゅ",
      "スコア": "4281/4300(99.55%)",
      "PG": 2133,
      "GR": 15,
      "BPI": 71.74
    },
    {
      "順位": 5,
      "LR2ID": "170023",
      "プレイヤー": "雪花ラミィ",
      "スコア": "4269/4300(99.27%)",
      "PG": 2123,
      "GR": 23,
      "BPI": 58.89
    },
    {
      "順位": 6,
      "LR2ID": "184466",
      "プレイヤー": "なんこつ君",
      "スコア": "4254/4300(98.93%)",
      "PG": 2105,
      "GR": 44,
      "BPI": 48.0
    },
    {
      "順位": 7,
      "LR2ID": "105437",
      "プレイヤー": "comet*",
      "スコア": "4253/4300(98.9%)",
      "PG": 2105,
      "GR": 43,
      "BPI": 47.39
    },
    {
      "順位": 8,
      "LR2ID": "140958",
      "プレイヤー": "浦和ハナコ",
      "スコア": "4250/4300(98.83%)",
      "PG": 2100,
      "GR": 50,
      "BPI": 45.62
    },
    {
      "順位": 9,
      "LR2ID": "158558",
      "プレイヤー": "ののか福丼",
      "スコア": "4246/4300(98.74%)",
      "PG": 2103,
      "GR": 40,
      "BPI": 43.4
    },
    {
      "順位": 10,
      "LR2ID": "36363",
      "プレイヤー": "フリーナ",
      "スコア": "4229/4300(98.34%)",
      "PG": 2079,
      "GR": 71,
      "BPI": 35.25
    },
    {
      "順位": 11,
      "LR2ID": "102160",
      "プレイヤー": "杏山カズサ",
      "スコア": "4224/4300(98.23%)",
      "PG": 2077,
      "GR": 70,
      "BPI": 33.15
    },
    {
      "順位": 12,
      "LR2ID": "116225",
      "プレイヤー": "各務チヒロ",
      "スコア": "4212/4300(97.95%)",
      "PG": 2067,
      "GR": 78,
      "BPI": 28.51
    },
    {
      "順位": 13,
      "LR2ID": "180026",
      "プレイヤー": "ｷｱﾗ･ﾌｨﾘｰﾅ",
      "スコア": "4211/4300(97.93%)",
      "PG": 2068,
      "GR": 75,
      "BPI": 28.14
    },
    {
      "順位": 14,
      "LR2ID": "94429",
      "プレイヤー": "神谷奈緒",
      "スコア": "4199/4300(97.65%)",
      "PG": 2050,
      "GR": 99,
      "BPI": 23.96
    }
  ],
  "29": [
    {
      "順位": 1,
      "LR2ID": "63505",
      "プレイヤー": "生塩ノア",
      "スコア": "3099/3102(99.9%)",
      "PG": 1548,
      "GR": 3,
      "BPI": 74.41
    },
    {
      "順位": 2,
      "LR2ID": "187038",
      "プレイヤー": "PanPiano",
      "スコア": "3096/3102(99.8%)",
      "PG": 1545,
      "GR": 6,
      "BPI": 63.92
    },
    {
      "順位": 3,
      "LR2ID": "166001",
      "プレイヤー": "しっちゅ",
      "スコア": "3089/3102(99.58%)",
      "PG": 1539,
      "GR": 11,
      "BPI": 51.68
    },
    {
      "順位": 4,
      "LR2ID": "116225",
      "プレイヤー": "各務チヒロ",
      "スコア": "3083/3102(99.38%)",
      "PG": 1535,
      "GR": 13,
      "BPI": 45.41
    },
    {
      "順位": 5,
      "LR2ID": "105437",
      "プレイヤー": "comet*",
      "スコア": "3078/3102(99.22%)",
      "PG": 1528,
      "GR": 22,
      "BPI": 41.44
    },
    {
      "順位": 5,
      "LR2ID": "158558",
      "プレイヤー": "ののか福丼",
      "スコア": "3078/3102(99.22%)",
      "PG": 1529,
      "GR": 20,
      "BPI": 41.44
    },
    {
      "順位": 7,
      "LR2ID": "140958",
      "プレイヤー": "浦和ハナコ",
      "スコア": "3074/3102(99.09%)",
      "PG": 1524,
      "GR": 26,
      "BPI": 38.77
    },
    {
      "順位": 8,
      "LR2ID": "184466",
      "プレイヤー": "なんこつ君",
      "スコア": "3070/3102(98.96%)",
      "PG": 1521,
      "GR": 28,
      "BPI": 36.42
    },
    {
      "順位": 9,
      "LR2ID": "36363",
      "プレイヤー": "フリーナ",
      "スコア": "3052/3102(98.38%)",
      "PG": 1506,
      "GR": 40,
      "BPI": 28.25
    },
    {
      "順位": 10,
      "LR2ID": "94429",
      "プレイヤー": "神谷奈緒",
      "スコア": "3045/3102(98.16%)",
      "PG": 1497,
      "GR": 51,
      "BPI": 25.74
    },
    {
      "順位": 11,
      "LR2ID": "180026",
      "プレイヤー": "ｷｱﾗ･ﾌｨﾘｰﾅ",
      "スコア": "2966/3102(95.61%)",
      "PG": 1426,
      "GR": 114,
      "BPI": 6.6
    },
    {
      "順位": 12,
      "LR2ID": "102160",
      "プレイヤー": "杏山カズサ",
      "スコア": "2802/3102(90.32%)",
      "PG": 1276,
      "GR": 250,
      "BPI": -15
    }
  ],
  "30": [
    {
      "順位": 1,
      "LR2ID": "63505",
      "プレイヤー": "生塩ノア",
      "スコア": "3195/3238(98.67%)",
      "PG": 1579,
      "GR": 37,
      "BPI": 89.06
    },
    {
      "順位": 2,
      "LR2ID": "101654",
      "プレイヤー": "ウドフル君",
      "スコア": "3182/3238(98.27%)",
      "PG": 1565,
      "GR": 52,
      "BPI": 77.79
    },
    {
      "順位": 3,
      "LR2ID": "105437",
      "プレイヤー": "comet*",
      "スコア": "3175/3238(98.05%)",
      "PG": 1561,
      "GR": 53,
      "BPI": 72.64
    },
    {
      "順位": 4,
      "LR2ID": "158558",
      "プレイヤー": "ののか福丼",
      "スコア": "3146/3238(97.15%)",
      "PG": 1538,
      "GR": 70,
      "BPI": 55.38
    },
    {
      "順位": 5,
      "LR2ID": "116225",
      "プレイヤー": "各務チヒロ",
      "スコア": "3136/3238(96.84%)",
      "PG": 1524,
      "GR": 88,
      "BPI": 50.45
    },
    {
      "順位": 5,
      "LR2ID": "36363",
      "プレイヤー": "フリーナ",
      "スコア": "3136/3238(96.84%)",
      "PG": 1531,
      "GR": 74,
      "BPI": 50.45
    },
    {
      "順位": 7,
      "LR2ID": "140958",
      "プレイヤー": "浦和ハナコ",
      "スコア": "3127/3238(96.57%)",
      "PG": 1511,
      "GR": 105,
      "BPI": 46.31
    },
    {
      "順位": 8,
      "LR2ID": "184466",
      "プレイヤー": "なんこつ君",
      "スコア": "3106/3238(95.92%)",
      "PG": 1501,
      "GR": 104,
      "BPI": 37.54
    },
    {
      "順位": 9,
      "LR2ID": "94429",
      "プレイヤー": "神谷奈緒",
      "スコア": "3066/3238(94.68%)",
      "PG": 1462,
      "GR": 142,
      "BPI": 22.96
    },
    {
      "順位": 10,
      "LR2ID": "166001",
      "プレイヤー": "しっちゅ",
      "スコア": "3020/3238(93.26%)",
      "PG": 1442,
      "GR": 136,
      "BPI": 7.35
    },
    {
      "順位": 11,
      "LR2ID": "180026",
      "プレイヤー": "ｷｱﾗ･ﾌｨﾘｰﾅ",
      "スコア": "2941/3238(90.82%)",
      "PG": 1362,
      "GR": 217,
      "BPI": -15
    },
    {
      "順位": 12,
      "LR2ID": "102160",
      "プレイヤー": "杏山カズサ",
      "スコア": "2893/3238(89.34%)",
      "PG": 1326,
      "GR": 241,
      "BPI": -15
    }
  ],
  "31": [
    {
      "順位": 1,
      "LR2ID": "187038",
      "プレイヤー": "PanPiano",
      "スコア": "3946/4108(96.05%)",
      "PG": 1920,
      "GR": 106,
      "BPI": 66.3
    },
    {
      "順位": 2,
      "LR2ID": "63505",
      "プレイヤー": "生塩ノア",
      "スコア": "3939/4108(95.88%)",
      "PG": 1893,
      "GR": 153,
      "BPI": 64.19
    },
    {
      "順位": 3,
      "LR2ID": "140958",
      "プレイヤー": "浦和ハナコ",
      "スコア": "3860/4108(93.96%)",
      "PG": 1834,
      "GR": 192,
      "BPI": 44.16
    },
    {
      "順位": 4,
      "LR2ID": "184466",
      "プレイヤー": "なんこつ君",
      "スコア": "3843/4108(93.54%)",
      "PG": 1822,
      "GR": 199,
      "BPI": 40.48
    },
    {
      "順位": 5,
      "LR2ID": "105437",
      "プレイヤー": "comet*",
      "スコア": "3829/4108(93.2%)",
      "PG": 1817,
      "GR": 195,
      "BPI": 37.57
    },
    {
      "順位": 6,
      "LR2ID": "158558",
      "プレイヤー": "ののか福丼",
      "スコア": "3817/4108(92.91%)",
      "PG": 1806,
      "GR": 205,
      "BPI": 35.14
    },
    {
      "順位": 7,
      "LR2ID": "36363",
      "プレイヤー": "フリーナ",
      "スコア": "3806/4108(92.64%)",
      "PG": 1785,
      "GR": 236,
      "BPI": 32.97
    },
    {
      "順位": 8,
      "LR2ID": "170023",
      "プレイヤー": "雪花ラミィ",
      "スコア": "3758/4108(91.48%)",
      "PG": 1757,
      "GR": 244,
      "BPI": 23.92
    },
    {
      "順位": 9,
      "LR2ID": "94429",
      "プレイヤー": "神谷奈緒",
      "スコア": "3745/4108(91.16%)",
      "PG": 1740,
      "GR": 265,
      "BPI": 21.55
    },
    {
      "順位": 10,
      "LR2ID": "116225",
      "プレイヤー": "各務チヒロ",
      "スコア": "3722/4108(90.6%)",
      "PG": 1733,
      "GR": 256,
      "BPI": 17.41
    }
  ],
  "32": [
    {
      "順位": 1,
      "LR2ID": "63505",
      "プレイヤー": "生塩ノア",
      "スコア": "4813/4944(97.35%)",
      "PG": 2367,
      "GR": 79,
      "BPI": 75.11
    },
    {
      "順位": 2,
      "LR2ID": "105437",
      "プレイヤー": "comet*",
      "スコア": "4617/4944(93.38%)",
      "PG": 2196,
      "GR": 225,
      "BPI": 30.72
    },
    {
      "順位": 3,
      "LR2ID": "140958",
      "プレイヤー": "浦和ハナコ",
      "スコア": "4609/4944(93.22%)",
      "PG": 2181,
      "GR": 247,
      "BPI": 29.38
    },
    {
      "順位": 4,
      "LR2ID": "170023",
      "プレイヤー": "雪花ラミィ",
      "スコア": "4599/4944(93.02%)",
      "PG": 2188,
      "GR": 223,
      "BPI": 27.72
    },
    {
      "順位": 5,
      "LR2ID": "102160",
      "プレイヤー": "杏山カズサ",
      "スコア": "4596/4944(92.96%)",
      "PG": 2191,
      "GR": 214,
      "BPI": 27.23
    },
    {
      "順位": 6,
      "LR2ID": "158558",
      "プレイヤー": "ののか福丼",
      "スコア": "4589/4944(92.81%)",
      "PG": 2175,
      "GR": 239,
      "BPI": 26.09
    },
    {
      "順位": 7,
      "LR2ID": "94429",
      "プレイヤー": "神谷奈緒",
      "スコア": "4580/4944(92.63%)",
      "PG": 2165,
      "GR": 250,
      "BPI": 24.64
    },
    {
      "順位": 8,
      "LR2ID": "36363",
      "プレイヤー": "フリーナ",
      "スコア": "4533/4944(91.68%)",
      "PG": 2130,
      "GR": 273,
      "BPI": 17.25
    },
    {
      "順位": 9,
      "LR2ID": "116225",
      "プレイヤー": "各務チヒロ",
      "スコア": "4396/4944(88.91%)",
      "PG": 2029,
      "GR": 338,
      "BPI": -15
    },
    {
      "順位": 10,
      "LR2ID": "187038",
      "プレイヤー": "PanPiano",
      "スコア": "3718/4944(75.2%)",
      "PG": 1472,
      "GR": 774,
      "BPI": -15
    }
  ],
  "33": [
    {
      "順位": 1,
      "LR2ID": "187038",
      "プレイヤー": "PanPiano",
      "スコア": "3788/3860(98.13%)",
      "PG": 1861,
      "GR": 66,
      "BPI": 65.07
    },
    {
      "順位": 2,
      "LR2ID": "63505",
      "プレイヤー": "生塩ノア",
      "スコア": "3761/3860(97.43%)",
      "PG": 1839,
      "GR": 83,
      "BPI": 54.52
    },
    {
      "順位": 3,
      "LR2ID": "105437",
      "プレイヤー": "comet*",
      "スコア": "3715/3860(96.24%)",
      "PG": 1793,
      "GR": 129,
      "BPI": 41.15
    },
    {
      "順位": 4,
      "LR2ID": "140958",
      "プレイヤー": "浦和ハナコ",
      "スコア": "3703/3860(95.93%)",
      "PG": 1790,
      "GR": 123,
      "BPI": 38.23
    },
    {
      "順位": 5,
      "LR2ID": "116225",
      "プレイヤー": "各務チヒロ",
      "スコア": "3676/3860(95.23%)",
      "PG": 1778,
      "GR": 120,
      "BPI": 32.22
    },
    {
      "順位": 6,
      "LR2ID": "36363",
      "プレイヤー": "フリーナ",
      "スコア": "3668/3860(95.02%)",
      "PG": 1758,
      "GR": 152,
      "BPI": 30.57
    },
    {
      "順位": 7,
      "LR2ID": "170023",
      "プレイヤー": "雪花ラミィ",
      "スコア": "3641/3860(94.32%)",
      "PG": 1747,
      "GR": 147,
      "BPI": 25.29
    },
    {
      "順位": 8,
      "LR2ID": "94429",
      "プレイヤー": "神谷奈緒",
      "スコア": "3625/3860(93.91%)",
      "PG": 1731,
      "GR": 163,
      "BPI": 22.35
    },
    {
      "順位": 9,
      "LR2ID": "102160",
      "プレイヤー": "杏山カズサ",
      "スコア": "3592/3860(93.05%)",
      "PG": 1709,
      "GR": 174,
      "BPI": 16.59
    }
  ],
  "34": [
    {
      "順位": 1,
      "LR2ID": "174817",
      "プレイヤー": "マイマイ君",
      "スコア": "3444/3486(98.79%)",
      "PG": 1703,
      "GR": 38,
      "BPI": 72.76
    },
    {
      "順位": 2,
      "LR2ID": "63505",
      "プレイヤー": "生塩ノア",
      "スコア": "3418/3486(98.04%)",
      "PG": 1682,
      "GR": 54,
      "BPI": 54.91
    },
    {
      "順位": 3,
      "LR2ID": "105437",
      "プレイヤー": "comet*",
      "スコア": "3397/3486(97.44%)",
      "PG": 1664,
      "GR": 69,
      "BPI": 44.3
    },
    {
      "順位": 4,
      "LR2ID": "116225",
      "プレイヤー": "各務チヒロ",
      "スコア": "3386/3486(97.13%)",
      "PG": 1654,
      "GR": 78,
      "BPI": 39.5
    },
    {
      "順位": 5,
      "LR2ID": "180026",
      "プレイヤー": "ｷｱﾗ･ﾌｨﾘｰﾅ",
      "スコア": "3345/3486(95.95%)",
      "PG": 1619,
      "GR": 107,
      "BPI": 24.36
    },
    {
      "順位": 6,
      "LR2ID": "140958",
      "プレイヤー": "浦和ハナコ",
      "スコア": "3322/3486(95.29%)",
      "PG": 1590,
      "GR": 142,
      "BPI": 16.93
    },
    {
      "順位": 7,
      "LR2ID": "102160",
      "プレイヤー": "杏山カズサ",
      "スコア": "3307/3486(94.86%)",
      "PG": 1589,
      "GR": 129,
      "BPI": 12.24
    },
    {
      "順位": 8,
      "LR2ID": "36363",
      "プレイヤー": "フリーナ",
      "スコア": "3305/3486(94.8%)",
      "PG": 1580,
      "GR": 145,
      "BPI": 11.62
    }
  ],
  "35": [
    {
      "順位": 1,
      "LR2ID": "63505",
      "プレイヤー": "生塩ノア",
      "スコア": "3014/3060(98.49%)",
      "PG": 1488,
      "GR": 38,
      "BPI": 48.06
    },
    {
      "順位": 2,
      "LR2ID": "105437",
      "プレイヤー": "comet*",
      "スコア": "2990/3060(97.71%)",
      "PG": 1467,
      "GR": 56,
      "BPI": 32.54
    },
    {
      "順位": 3,
      "LR2ID": "116225",
      "プレイヤー": "各務チヒロ",
      "スコア": "2989/3060(97.67%)",
      "PG": 1469,
      "GR": 51,
      "BPI": 31.99
    },
    {
      "順位": 3,
      "LR2ID": "140958",
      "プレイヤー": "浦和ハナコ",
      "スコア": "2989/3060(97.67%)",
      "PG": 1462,
      "GR": 65,
      "BPI": 31.99
    },
    {
      "順位": 5,
      "LR2ID": "36363",
      "プレイヤー": "フリーナ",
      "スコア": "2952/3060(96.47%)",
      "PG": 1428,
      "GR": 96,
      "BPI": 14.09
    },
    {
      "順位": 6,
      "LR2ID": "102160",
      "プレイヤー": "杏山カズサ",
      "スコア": "2941/3060(96.11%)",
      "PG": 1426,
      "GR": 89,
      "BPI": 9.2
    },
    {
      "順位": 7,
      "LR2ID": "94429",
      "プレイヤー": "神谷奈緒",
      "スコア": "2919/3060(95.39%)",
      "PG": 1399,
      "GR": 121,
      "BPI": -15
    }
  ],
  "36": [
    {
      "順位": 1,
      "LR2ID": "63505",
      "プレイヤー": "生塩ノア",
      "スコア": "6268/6350(98.7%)",
      "PG": 3093,
      "GR": 82,
      "BPI": 75.18
    },
    {
      "順位": 2,
      "LR2ID": "105437",
      "プレイヤー": "comet*",
      "スコア": "6208/6350(97.76%)",
      "PG": 3037,
      "GR": 134,
      "BPI": 52.31
    },
    {
      "順位": 3,
      "LR2ID": "116225",
      "プレイヤー": "各務チヒロ",
      "スコア": "6153/6350(96.89%)",
      "PG": 2992,
      "GR": 169,
      "BPI": 37.42
    },
    {
      "順位": 4,
      "LR2ID": "94429",
      "プレイヤー": "神谷奈緒",
      "スコア": "6140/6350(96.69%)",
      "PG": 2981,
      "GR": 178,
      "BPI": 34.35
    },
    {
      "順位": 5,
      "LR2ID": "140958",
      "プレイヤー": "浦和ハナコ",
      "スコア": "6091/6350(95.92%)",
      "PG": 2927,
      "GR": 237,
      "BPI": 23.72
    },
    {
      "順位": 6,
      "LR2ID": "36363",
      "プレイヤー": "フリーナ",
      "スコア": "6075/6350(95.66%)",
      "PG": 2913,
      "GR": 249,
      "BPI": 20.47
    }
  ],
  "37": [
    {
      "順位": 1,
      "LR2ID": "185932",
      "プレイヤー": "idiatic",
      "スコア": "4170/4194(99.42%)",
      "PG": 2074,
      "GR": 22,
      "BPI": 100.0
    },
    {
      "順位": 2,
      "LR2ID": "187635",
      "プレイヤー": "LR2oraja",
      "スコア": "4158/4194(99.14%)",
      "PG": 2061,
      "GR": 36,
      "BPI": 87.44
    },
    {
      "順位": 3,
      "LR2ID": "63505",
      "プレイヤー": "生塩ノア",
      "スコア": "4157/4194(99.11%)",
      "PG": 2063,
      "GR": 31,
      "BPI": 86.58
    },
    {
      "順位": 4,
      "LR2ID": "166001",
      "プレイヤー": "しっちゅ",
      "スコア": "4140/4194(98.71%)",
      "PG": 2047,
      "GR": 46,
      "BPI": 74.41
    },
    {
      "順位": 5,
      "LR2ID": "174817",
      "プレイヤー": "マイマイ君",
      "スコア": "4137/4194(98.64%)",
      "PG": 2045,
      "GR": 47,
      "BPI": 72.64
    },
    {
      "順位": 6,
      "LR2ID": "184466",
      "プレイヤー": "なんこつ君",
      "スコア": "4129/4194(98.45%)",
      "PG": 2039,
      "GR": 51,
      "BPI": 68.27
    },
    {
      "順位": 7,
      "LR2ID": "61149",
      "プレイヤー": "卯月神楽",
      "スコア": "4113/4194(98.06%)",
      "PG": 2019,
      "GR": 75,
      "BPI": 60.79
    },
    {
      "順位": 8,
      "LR2ID": "187634",
      "プレイヤー": "大和赤驥",
      "スコア": "4112/4194(98.04%)",
      "PG": 2019,
      "GR": 74,
      "BPI": 60.36
    },
    {
      "順位": 9,
      "LR2ID": "163213",
      "プレイヤー": "のせちゃ",
      "スコア": "4107/4194(97.92%)",
      "PG": 2011,
      "GR": 85,
      "BPI": 58.31
    },
    {
      "順位": 10,
      "LR2ID": "186211",
      "プレイヤー": "与那国ﾋｶﾘ",
      "スコア": "4106/4194(97.9%)",
      "PG": 2017,
      "GR": 72,
      "BPI": 57.91
    },
    {
      "順位": 11,
      "LR2ID": "170023",
      "プレイヤー": "雪花ラミィ",
      "スコア": "4085/4194(97.4%)",
      "PG": 1998,
      "GR": 89,
      "BPI": 50.3
    },
    {
      "順位": 12,
      "LR2ID": "105437",
      "プレイヤー": "comet*",
      "スコア": "4082/4194(97.32%)",
      "PG": 1986,
      "GR": 110,
      "BPI": 49.32
    },
    {
      "順位": 13,
      "LR2ID": "102160",
      "プレイヤー": "杏山カズサ",
      "スコア": "4016/4194(95.75%)",
      "PG": 1936,
      "GR": 144,
      "BPI": 31.59
    },
    {
      "順位": 14,
      "LR2ID": "140958",
      "プレイヤー": "浦和ハナコ",
      "スコア": "4007/4194(95.54%)",
      "PG": 1929,
      "GR": 149,
      "BPI": 29.57
    },
    {
      "順位": 15,
      "LR2ID": "116225",
      "プレイヤー": "各務チヒロ",
      "スコア": "4002/4194(95.42%)",
      "PG": 1928,
      "GR": 146,
      "BPI": 28.48
    },
    {
      "順位": 16,
      "LR2ID": "94429",
      "プレイヤー": "神谷奈緒",
      "スコア": "3983/4194(94.96%)",
      "PG": 1902,
      "GR": 179,
      "BPI": 24.47
    },
    {
      "順位": 17,
      "LR2ID": "36363",
      "プレイヤー": "フリーナ",
      "スコア": "3968/4194(94.61%)",
      "PG": 1886,
      "GR": 196,
      "BPI": 21.45
    },
    {
      "順位": 18,
      "LR2ID": "141062",
      "プレイヤー": "MITTUN",
      "スコア": "3957/4194(94.34%)",
      "PG": 1874,
      "GR": 209,
      "BPI": 19.29
    },
    {
      "順位": 19,
      "LR2ID": "180026",
      "プレイヤー": "ｷｱﾗ･ﾌｨﾘｰﾅ",
      "スコア": "3936/4194(93.84%)",
      "PG": 1855,
      "GR": 226,
      "BPI": 15.28
    }
  ],
  "38": [
    {
      "順位": 1,
      "LR2ID": "187038",
      "プレイヤー": "PanPiano",
      "スコア": "3417/3420(99.91%)",
      "PG": 1707,
      "GR": 3,
      "BPI": 70.25
    },
    {
      "順位": 1,
      "LR2ID": "185932",
      "プレイヤー": "idiatic",
      "スコア": "3417/3420(99.91%)",
      "PG": 1707,
      "GR": 3,
      "BPI": 70.25
    },
    {
      "順位": 3,
      "LR2ID": "63505",
      "プレイヤー": "生塩ノア",
      "スコア": "3416/3420(99.88%)",
      "PG": 1706,
      "GR": 4,
      "BPI": 65.2
    },
    {
      "順位": 4,
      "LR2ID": "187635",
      "プレイヤー": "LR2oraja",
      "スコア": "3413/3420(99.79%)",
      "PG": 1703,
      "GR": 7,
      "BPI": 55.07
    },
    {
      "順位": 5,
      "LR2ID": "184466",
      "プレイヤー": "なんこつ君",
      "スコア": "3410/3420(99.7%)",
      "PG": 1701,
      "GR": 8,
      "BPI": 48.37
    },
    {
      "順位": 5,
      "LR2ID": "174817",
      "プレイヤー": "マイマイ君",
      "スコア": "3410/3420(99.7%)",
      "PG": 1701,
      "GR": 8,
      "BPI": 48.37
    },
    {
      "順位": 7,
      "LR2ID": "186211",
      "プレイヤー": "与那国ﾋｶﾘ",
      "スコア": "3409/3420(99.67%)",
      "PG": 1699,
      "GR": 11,
      "BPI": 46.54
    },
    {
      "順位": 7,
      "LR2ID": "170023",
      "プレイヤー": "雪花ラミィ",
      "スコア": "3409/3420(99.67%)",
      "PG": 1699,
      "GR": 11,
      "BPI": 46.54
    },
    {
      "順位": 9,
      "LR2ID": "140958",
      "プレイヤー": "浦和ハナコ",
      "スコア": "3403/3420(99.5%)",
      "PG": 1693,
      "GR": 17,
      "BPI": 37.93
    },
    {
      "順位": 10,
      "LR2ID": "187634",
      "プレイヤー": "大和赤驥",
      "スコア": "3401/3420(99.44%)",
      "PG": 1693,
      "GR": 15,
      "BPI": 35.65
    },
    {
      "順位": 11,
      "LR2ID": "61149",
      "プレイヤー": "卯月神楽",
      "スコア": "3400/3420(99.41%)",
      "PG": 1690,
      "GR": 20,
      "BPI": 34.59
    },
    {
      "順位": 12,
      "LR2ID": "105437",
      "プレイヤー": "comet*",
      "スコア": "3399/3420(99.38%)",
      "PG": 1689,
      "GR": 21,
      "BPI": 33.58
    },
    {
      "順位": 13,
      "LR2ID": "163213",
      "プレイヤー": "のせちゃ",
      "スコア": "3397/3420(99.32%)",
      "PG": 1688,
      "GR": 21,
      "BPI": 31.66
    },
    {
      "順位": 13,
      "LR2ID": "158558",
      "プレイヤー": "ののか福丼",
      "スコア": "3397/3420(99.32%)",
      "PG": 1690,
      "GR": 17,
      "BPI": 31.66
    },
    {
      "順位": 15,
      "LR2ID": "181781",
      "プレイヤー": "王雪",
      "スコア": "3394/3420(99.23%)",
      "PG": 1686,
      "GR": 22,
      "BPI": 29.02
    },
    {
      "順位": 16,
      "LR2ID": "116225",
      "プレイヤー": "各務チヒロ",
      "スコア": "3393/3420(99.21%)",
      "PG": 1683,
      "GR": 27,
      "BPI": 28.2
    },
    {
      "順位": 16,
      "LR2ID": "36363",
      "プレイヤー": "フリーナ",
      "スコア": "3393/3420(99.21%)",
      "PG": 1685,
      "GR": 23,
      "BPI": 28.2
    },
    {
      "順位": 18,
      "LR2ID": "102160",
      "プレイヤー": "杏山カズサ",
      "スコア": "3392/3420(99.18%)",
      "PG": 1683,
      "GR": 26,
      "BPI": 27.4
    },
    {
      "順位": 19,
      "LR2ID": "180026",
      "プレイヤー": "ｷｱﾗ･ﾌｨﾘｰﾅ",
      "スコア": "3391/3420(99.15%)",
      "PG": 1686,
      "GR": 19,
      "BPI": 26.63
    },
    {
      "順位": 20,
      "LR2ID": "94429",
      "プレイヤー": "神谷奈緒",
      "スコア": "3383/3420(98.91%)",
      "PG": 1673,
      "GR": 37,
      "BPI": 21.07
    },
    {
      "順位": 21,
      "LR2ID": "141062",
      "プレイヤー": "MITTUN",
      "スコア": "3357/3420(98.15%)",
      "PG": 1649,
      "GR": 59,
      "BPI": 7.12
    }
  ],
  "39": [
    {
      "順位": 1,
      "LR2ID": "185932",
      "プレイヤー": "idiatic",
      "スコア": "3672/3702(99.18%)",
      "PG": 1821,
      "GR": 30,
      "BPI": 81.45
    },
    {
      "順位": 2,
      "LR2ID": "174817",
      "プレイヤー": "マイマイ君",
      "スコア": "3667/3702(99.05%)",
      "PG": 1817,
      "GR": 33,
      "BPI": 76.75
    },
    {
      "順位": 3,
      "LR2ID": "184466",
      "プレイヤー": "なんこつ君",
      "スコア": "3649/3702(98.56%)",
      "PG": 1798,
      "GR": 53,
      "BPI": 63.69
    },
    {
      "順位": 4,
      "LR2ID": "63505",
      "プレイヤー": "生塩ノア",
      "スコア": "3640/3702(98.32%)",
      "PG": 1792,
      "GR": 56,
      "BPI": 58.59
    },
    {
      "順位": 5,
      "LR2ID": "186211",
      "プレイヤー": "与那国ﾋｶﾘ",
      "スコア": "3625/3702(97.92%)",
      "PG": 1776,
      "GR": 73,
      "BPI": 51.34
    },
    {
      "順位": 6,
      "LR2ID": "181781",
      "プレイヤー": "王雪",
      "スコア": "3608/3702(97.46%)",
      "PG": 1765,
      "GR": 78,
      "BPI": 44.43
    },
    {
      "順位": 7,
      "LR2ID": "187634",
      "プレイヤー": "大和赤驥",
      "スコア": "3605/3702(97.37%)",
      "PG": 1760,
      "GR": 85,
      "BPI": 43.32
    },
    {
      "順位": 8,
      "LR2ID": "105437",
      "プレイヤー": "comet*",
      "スコア": "3595/3702(97.1%)",
      "PG": 1748,
      "GR": 99,
      "BPI": 39.81
    },
    {
      "順位": 8,
      "LR2ID": "158558",
      "プレイヤー": "ののか福丼",
      "スコア": "3595/3702(97.1%)",
      "PG": 1753,
      "GR": 89,
      "BPI": 39.81
    },
    {
      "順位": 10,
      "LR2ID": "140958",
      "プレイヤー": "浦和ハナコ",
      "スコア": "3593/3702(97.05%)",
      "PG": 1750,
      "GR": 93,
      "BPI": 39.13
    },
    {
      "順位": 11,
      "LR2ID": "163213",
      "プレイヤー": "のせちゃ",
      "スコア": "3592/3702(97.02%)",
      "PG": 1742,
      "GR": 108,
      "BPI": 38.8
    },
    {
      "順位": 12,
      "LR2ID": "61149",
      "プレイヤー": "卯月神楽",
      "スコア": "3587/3702(96.89%)",
      "PG": 1740,
      "GR": 107,
      "BPI": 37.17
    },
    {
      "順位": 13,
      "LR2ID": "94429",
      "プレイヤー": "神谷奈緒",
      "スコア": "3582/3702(96.75%)",
      "PG": 1739,
      "GR": 104,
      "BPI": 35.59
    },
    {
      "順位": 14,
      "LR2ID": "116225",
      "プレイヤー": "各務チヒロ",
      "スコア": "3573/3702(96.51%)",
      "PG": 1733,
      "GR": 107,
      "BPI": 32.87
    },
    {
      "順位": 15,
      "LR2ID": "102160",
      "プレイヤー": "杏山カズサ",
      "スコア": "3545/3702(95.75%)",
      "PG": 1703,
      "GR": 139,
      "BPI": 25.16
    },
    {
      "順位": 16,
      "LR2ID": "36363",
      "プレイヤー": "フリーナ",
      "スコア": "3537/3702(95.54%)",
      "PG": 1695,
      "GR": 147,
      "BPI": 23.12
    }
  ],
  "40": [
    {
      "順位": 1,
      "LR2ID": "63505",
      "プレイヤー": "生塩ノア",
      "スコア": "4319/4360(99.05%)",
      "PG": 2141,
      "GR": 37,
      "BPI": 72.77
    },
    {
      "順位": 2,
      "LR2ID": "187038",
      "プレイヤー": "PanPiano",
      "スコア": "4302/4360(98.66%)",
      "PG": 2125,
      "GR": 52,
      "BPI": 61.35
    },
    {
      "順位": 3,
      "LR2ID": "185932",
      "プレイヤー": "idiatic",
      "スコア": "4299/4360(98.6%)",
      "PG": 2120,
      "GR": 59,
      "BPI": 59.65
    },
    {
      "順位": 4,
      "LR2ID": "61149",
      "プレイヤー": "卯月神楽",
      "スコア": "4276/4360(98.07%)",
      "PG": 2097,
      "GR": 82,
      "BPI": 48.53
    },
    {
      "順位": 5,
      "LR2ID": "184466",
      "プレイヤー": "なんこつ君",
      "スコア": "4264/4360(97.79%)",
      "PG": 2087,
      "GR": 90,
      "BPI": 43.7
    },
    {
      "順位": 6,
      "LR2ID": "105437",
      "プレイヤー": "comet*",
      "スコア": "4257/4360(97.63%)",
      "PG": 2084,
      "GR": 89,
      "BPI": 41.1
    },
    {
      "順位": 7,
      "LR2ID": "140958",
      "プレイヤー": "浦和ハナコ",
      "スコア": "4247/4360(97.4%)",
      "PG": 2067,
      "GR": 113,
      "BPI": 37.62
    },
    {
      "順位": 8,
      "LR2ID": "187650",
      "プレイヤー": "KEYJET",
      "スコア": "4245/4360(97.36%)",
      "PG": 2067,
      "GR": 111,
      "BPI": 36.95
    },
    {
      "順位": 9,
      "LR2ID": "170023",
      "プレイヤー": "雪花ラミィ",
      "スコア": "4243/4360(97.31%)",
      "PG": 2073,
      "GR": 97,
      "BPI": 36.29
    },
    {
      "順位": 10,
      "LR2ID": "163213",
      "プレイヤー": "のせちゃ",
      "スコア": "4242/4360(97.29%)",
      "PG": 2065,
      "GR": 112,
      "BPI": 35.96
    },
    {
      "順位": 11,
      "LR2ID": "186211",
      "プレイヤー": "与那国ﾋｶﾘ",
      "スコア": "4228/4360(96.97%)",
      "PG": 2054,
      "GR": 120,
      "BPI": 31.58
    },
    {
      "順位": 12,
      "LR2ID": "181781",
      "プレイヤー": "王雪",
      "スコア": "4220/4360(96.78%)",
      "PG": 2042,
      "GR": 136,
      "BPI": 29.22
    },
    {
      "順位": 13,
      "LR2ID": "94429",
      "プレイヤー": "神谷奈緒",
      "スコア": "4217/4360(96.72%)",
      "PG": 2045,
      "GR": 127,
      "BPI": 28.36
    },
    {
      "順位": 14,
      "LR2ID": "187634",
      "プレイヤー": "大和赤驥",
      "スコア": "4207/4360(96.49%)",
      "PG": 2035,
      "GR": 137,
      "BPI": 25.56
    },
    {
      "順位": 15,
      "LR2ID": "36363",
      "プレイヤー": "フリーナ",
      "スコア": "4199/4360(96.3%)",
      "PG": 2033,
      "GR": 133,
      "BPI": 23.4
    },
    {
      "順位": 16,
      "LR2ID": "116225",
      "プレイヤー": "各務チヒロ",
      "スコア": "4194/4360(96.19%)",
      "PG": 2021,
      "GR": 152,
      "BPI": 22.08
    },
    {
      "順位": 17,
      "LR2ID": "180026",
      "プレイヤー": "ｷｱﾗ･ﾌｨﾘｰﾅ",
      "スコア": "4077/4360(93.5%)",
      "PG": 1919,
      "GR": 239,
      "BPI": -15
    }
  ],
  "41": [
    {
      "順位": 1,
      "LR2ID": "63505",
      "プレイヤー": "生塩ノア",
      "スコア": "3413/3416(99.91%)",
      "PG": 1705,
      "GR": 3,
      "BPI": 100.0
    },
    {
      "順位": 2,
      "LR2ID": "185932",
      "プレイヤー": "idiatic",
      "スコア": "3410/3416(99.82%)",
      "PG": 1702,
      "GR": 6,
      "BPI": 85.7
    },
    {
      "順位": 3,
      "LR2ID": "61149",
      "プレイヤー": "卯月神楽",
      "スコア": "3379/3416(98.91%)",
      "PG": 1672,
      "GR": 35,
      "BPI": 44.58
    },
    {
      "順位": 4,
      "LR2ID": "184466",
      "プレイヤー": "なんこつ君",
      "スコア": "3375/3416(98.79%)",
      "PG": 1668,
      "GR": 39,
      "BPI": 42.02
    },
    {
      "順位": 5,
      "LR2ID": "105437",
      "プレイヤー": "comet*",
      "スコア": "3373/3416(98.74%)",
      "PG": 1666,
      "GR": 41,
      "BPI": 40.82
    },
    {
      "順位": 6,
      "LR2ID": "187634",
      "プレイヤー": "大和赤驥",
      "スコア": "3360/3416(98.36%)",
      "PG": 1654,
      "GR": 52,
      "BPI": 33.97
    },
    {
      "順位": 7,
      "LR2ID": "116225",
      "プレイヤー": "各務チヒロ",
      "スコア": "3358/3416(98.3%)",
      "PG": 1654,
      "GR": 50,
      "BPI": 33.04
    },
    {
      "順位": 8,
      "LR2ID": "94429",
      "プレイヤー": "神谷奈緒",
      "スコア": "3349/3416(98.03%)",
      "PG": 1644,
      "GR": 61,
      "BPI": 29.13
    },
    {
      "順位": 9,
      "LR2ID": "140958",
      "プレイヤー": "浦和ハナコ",
      "スコア": "3345/3416(97.92%)",
      "PG": 1643,
      "GR": 59,
      "BPI": 27.52
    },
    {
      "順位": 10,
      "LR2ID": "36363",
      "プレイヤー": "フリーナ",
      "スコア": "3337/3416(97.68%)",
      "PG": 1631,
      "GR": 75,
      "BPI": 24.49
    },
    {
      "順位": 11,
      "LR2ID": "181781",
      "プレイヤー": "王雪",
      "スコア": "3318/3416(97.13%)",
      "PG": 1612,
      "GR": 94,
      "BPI": 18.07
    },
    {
      "順位": 12,
      "LR2ID": "163213",
      "プレイヤー": "のせちゃ",
      "スコア": "3311/3416(96.92%)",
      "PG": 1606,
      "GR": 99,
      "BPI": 15.89
    }
  ],
  "42": [
    {
      "順位": 1,
      "LR2ID": "63505",
      "プレイヤー": "生塩ノア",
      "スコア": "4381/4444(98.58%)",
      "PG": 2160,
      "GR": 61,
      "BPI": 82.95
    },
    {
      "順位": 2,
      "LR2ID": "174817",
      "プレイヤー": "マイマイ君",
      "スコア": "4279/4444(96.28%)",
      "PG": 2075,
      "GR": 129,
      "BPI": 45.45
    },
    {
      "順位": 3,
      "LR2ID": "61149",
      "プレイヤー": "卯月神楽",
      "スコア": "4276/4444(96.21%)",
      "PG": 2077,
      "GR": 122,
      "BPI": 44.68
    },
    {
      "順位": 4,
      "LR2ID": "94429",
      "プレイヤー": "神谷奈緒",
      "スコア": "4264/4444(95.94%)",
      "PG": 2054,
      "GR": 156,
      "BPI": 41.72
    },
    {
      "順位": 5,
      "LR2ID": "170023",
      "プレイヤー": "雪花ラミィ",
      "スコア": "4250/4444(95.63%)",
      "PG": 2051,
      "GR": 148,
      "BPI": 38.45
    },
    {
      "順位": 6,
      "LR2ID": "105437",
      "プレイヤー": "comet*",
      "スコア": "4238/4444(95.36%)",
      "PG": 2029,
      "GR": 180,
      "BPI": 35.78
    },
    {
      "順位": 7,
      "LR2ID": "140958",
      "プレイヤー": "浦和ハナコ",
      "スコア": "4237/4444(95.34%)",
      "PG": 2030,
      "GR": 177,
      "BPI": 35.56
    },
    {
      "順位": 7,
      "LR2ID": "187634",
      "プレイヤー": "大和赤驥",
      "スコア": "4237/4444(95.34%)",
      "PG": 2031,
      "GR": 175,
      "BPI": 35.56
    },
    {
      "順位": 9,
      "LR2ID": "36363",
      "プレイヤー": "フリーナ",
      "スコア": "4217/4444(94.89%)",
      "PG": 2008,
      "GR": 201,
      "BPI": 31.34
    },
    {
      "順位": 10,
      "LR2ID": "158558",
      "プレイヤー": "ののか福丼",
      "スコア": "4205/4444(94.62%)",
      "PG": 2010,
      "GR": 185,
      "BPI": 28.92
    },
    {
      "順位": 11,
      "LR2ID": "116225",
      "プレイヤー": "各務チヒロ",
      "スコア": "4114/4444(92.57%)",
      "PG": 1951,
      "GR": 212,
      "BPI": 12.17
    }
  ],
  "43": [
    {
      "順位": 1,
      "LR2ID": "166001",
      "プレイヤー": "しっちゅ",
      "スコア": "3172/3186(99.56%)",
      "PG": 1580,
      "GR": 12,
      "BPI": 83.93
    },
    {
      "順位": 2,
      "LR2ID": "63505",
      "プレイヤー": "生塩ノア",
      "スコア": "3169/3186(99.46%)",
      "PG": 1576,
      "GR": 17,
      "BPI": 78.18
    },
    {
      "順位": 3,
      "LR2ID": "116225",
      "プレイヤー": "各務チヒロ",
      "スコア": "3162/3186(99.24%)",
      "PG": 1570,
      "GR": 22,
      "BPI": 67.69
    },
    {
      "順位": 4,
      "LR2ID": "105437",
      "プレイヤー": "comet*",
      "スコア": "3153/3186(98.96%)",
      "PG": 1560,
      "GR": 33,
      "BPI": 57.63
    },
    {
      "順位": 5,
      "LR2ID": "174817",
      "プレイヤー": "マイマイ君",
      "スコア": "3151/3186(98.9%)",
      "PG": 1558,
      "GR": 35,
      "BPI": 55.73
    },
    {
      "順位": 6,
      "LR2ID": "140958",
      "プレイヤー": "浦和ハナコ",
      "スコア": "3140/3186(98.55%)",
      "PG": 1549,
      "GR": 42,
      "BPI": 46.64
    },
    {
      "順位": 7,
      "LR2ID": "187634",
      "プレイヤー": "大和赤驥",
      "スコア": "3137/3186(98.46%)",
      "PG": 1547,
      "GR": 43,
      "BPI": 44.48
    },
    {
      "順位": 8,
      "LR2ID": "36363",
      "プレイヤー": "フリーナ",
      "スコア": "3131/3186(98.27%)",
      "PG": 1542,
      "GR": 47,
      "BPI": 40.46
    },
    {
      "順位": 9,
      "LR2ID": "186211",
      "プレイヤー": "与那国ﾋｶﾘ",
      "スコア": "3130/3186(98.24%)",
      "PG": 1540,
      "GR": 50,
      "BPI": 39.82
    },
    {
      "順位": 9,
      "LR2ID": "61149",
      "プレイヤー": "卯月神楽",
      "スコア": "3130/3186(98.24%)",
      "PG": 1540,
      "GR": 50,
      "BPI": 39.82
    },
    {
      "順位": 11,
      "LR2ID": "163213",
      "プレイヤー": "のせちゃ",
      "スコア": "3021/3186(94.82%)",
      "PG": 1437,
      "GR": 147,
      "BPI": -15
    },
    {
      "順位": 12,
      "LR2ID": "94429",
      "プレイヤー": "神谷奈緒",
      "スコア": "2997/3186(94.06%)",
      "PG": 1409,
      "GR": 179,
      "BPI": -15
    }
  ],
  "44": [
    {
      "順位": 1,
      "LR2ID": "105437",
      "プレイヤー": "comet*",
      "スコア": "4450/4492(99.06%)",
      "PG": 2207,
      "GR": 36,
      "BPI": 72.52
    },
    {
      "順位": 2,
      "LR2ID": "63505",
      "プレイヤー": "生塩ノア",
      "スコア": "4444/4492(98.93%)",
      "PG": 2202,
      "GR": 40,
      "BPI": 68.25
    },
    {
      "順位": 3,
      "LR2ID": "186211",
      "プレイヤー": "与那国ﾋｶﾘ",
      "スコア": "4439/4492(98.82%)",
      "PG": 2195,
      "GR": 49,
      "BPI": 65.04
    },
    {
      "順位": 4,
      "LR2ID": "187038",
      "プレイヤー": "PanPiano",
      "スコア": "4409/4492(98.15%)",
      "PG": 2163,
      "GR": 83,
      "BPI": 49.96
    },
    {
      "順位": 5,
      "LR2ID": "61149",
      "プレイヤー": "卯月神楽",
      "スコア": "4399/4492(97.92%)",
      "PG": 2158,
      "GR": 83,
      "BPI": 45.96
    },
    {
      "順位": 6,
      "LR2ID": "116225",
      "プレイヤー": "各務チヒロ",
      "スコア": "4393/4492(97.79%)",
      "PG": 2155,
      "GR": 83,
      "BPI": 43.72
    },
    {
      "順位": 7,
      "LR2ID": "140958",
      "プレイヤー": "浦和ハナコ",
      "スコア": "4391/4492(97.75%)",
      "PG": 2146,
      "GR": 99,
      "BPI": 43.0
    },
    {
      "順位": 8,
      "LR2ID": "36363",
      "プレイヤー": "フリーナ",
      "スコア": "4384/4492(97.59%)",
      "PG": 2143,
      "GR": 98,
      "BPI": 40.56
    },
    {
      "順位": 9,
      "LR2ID": "94429",
      "プレイヤー": "神谷奈緒",
      "スコア": "4348/4492(96.79%)",
      "PG": 2108,
      "GR": 132,
      "BPI": 29.62
    },
    {
      "順位": 10,
      "LR2ID": "187634",
      "プレイヤー": "大和赤驥",
      "スコア": "4320/4492(96.17%)",
      "PG": 2074,
      "GR": 172,
      "BPI": 22.33
    }
  ],
  "45": [
    {
      "順位": 1,
      "LR2ID": "105437",
      "プレイヤー": "comet*",
      "スコア": "3369/3534(95.33%)",
      "PG": 1623,
      "GR": 123,
      "BPI": 72.22
    },
    {
      "順位": 2,
      "LR2ID": "63505",
      "プレイヤー": "生塩ノア",
      "スコア": "3368/3534(95.3%)",
      "PG": 1624,
      "GR": 120,
      "BPI": 71.92
    },
    {
      "順位": 3,
      "LR2ID": "116225",
      "プレイヤー": "各務チヒロ",
      "スコア": "3332/3534(94.28%)",
      "PG": 1609,
      "GR": 114,
      "BPI": 61.99
    },
    {
      "順位": 4,
      "LR2ID": "186211",
      "プレイヤー": "与那国ﾋｶﾘ",
      "スコア": "3327/3534(94.14%)",
      "PG": 1606,
      "GR": 115,
      "BPI": 60.72
    },
    {
      "順位": 4,
      "LR2ID": "184466",
      "プレイヤー": "なんこつ君",
      "スコア": "3327/3534(94.14%)",
      "PG": 1589,
      "GR": 149,
      "BPI": 60.72
    },
    {
      "順位": 6,
      "LR2ID": "140958",
      "プレイヤー": "浦和ハナコ",
      "スコア": "3316/3534(93.83%)",
      "PG": 1587,
      "GR": 142,
      "BPI": 58.02
    },
    {
      "順位": 7,
      "LR2ID": "61149",
      "プレイヤー": "卯月神楽",
      "スコア": "3277/3534(92.72%)",
      "PG": 1558,
      "GR": 161,
      "BPI": 49.22
    },
    {
      "順位": 8,
      "LR2ID": "181781",
      "プレイヤー": "王雪",
      "スコア": "3272/3534(92.58%)",
      "PG": 1555,
      "GR": 162,
      "BPI": 48.16
    },
    {
      "順位": 9,
      "LR2ID": "94429",
      "プレイヤー": "神谷奈緒",
      "スコア": "3216/3534(91%)",
      "PG": 1475,
      "GR": 266,
      "BPI": 37.19
    },
    {
      "順位": 10,
      "LR2ID": "187634",
      "プレイヤー": "大和赤驥",
      "スコア": "3199/3534(90.52%)",
      "PG": 1485,
      "GR": 229,
      "BPI": 34.1
    },
    {
      "順位": 11,
      "LR2ID": "36363",
      "プレイヤー": "フリーナ",
      "スコア": "3192/3534(90.32%)",
      "PG": 1500,
      "GR": 192,
      "BPI": 32.86
    }
  ],
  "46": [
    {
      "順位": 1,
      "LR2ID": "63505",
      "プレイヤー": "生塩ノア",
      "スコア": "3586/3658(98.03%)",
      "PG": 1768,
      "GR": 50,
      "BPI": 80.13
    },
    {
      "順位": 2,
      "LR2ID": "105437",
      "プレイヤー": "comet*",
      "スコア": "3574/3658(97.7%)",
      "PG": 1762,
      "GR": 50,
      "BPI": 70.86
    },
    {
      "順位": 3,
      "LR2ID": "116225",
      "プレイヤー": "各務チヒロ",
      "スコア": "3569/3658(97.56%)",
      "PG": 1769,
      "GR": 31,
      "BPI": 67.3
    },
    {
      "順位": 4,
      "LR2ID": "61149",
      "プレイヤー": "卯月神楽",
      "スコア": "3544/3658(96.88%)",
      "PG": 1742,
      "GR": 60,
      "BPI": 51.47
    },
    {
      "順位": 5,
      "LR2ID": "36363",
      "プレイヤー": "フリーナ",
      "スコア": "3540/3658(96.77%)",
      "PG": 1745,
      "GR": 50,
      "BPI": 49.17
    },
    {
      "順位": 6,
      "LR2ID": "140958",
      "プレイヤー": "浦和ハナコ",
      "スコア": "3538/3658(96.71%)",
      "PG": 1740,
      "GR": 58,
      "BPI": 48.04
    },
    {
      "順位": 7,
      "LR2ID": "187634",
      "プレイヤー": "大和赤驥",
      "スコア": "3534/3658(96.61%)",
      "PG": 1735,
      "GR": 64,
      "BPI": 45.82
    },
    {
      "順位": 8,
      "LR2ID": "93985",
      "プレイヤー": "hakuo",
      "スコア": "3529/3658(96.47%)",
      "PG": 1724,
      "GR": 81,
      "BPI": 43.11
    },
    {
      "順位": 8,
      "LR2ID": "181781",
      "プレイヤー": "王雪",
      "スコア": "3529/3658(96.47%)",
      "PG": 1729,
      "GR": 71,
      "BPI": 43.11
    },
    {
      "順位": 10,
      "LR2ID": "162249",
      "プレイヤー": "西川海凪",
      "スコア": "3520/3658(96.22%)",
      "PG": 1729,
      "GR": 62,
      "BPI": 38.37
    },
    {
      "順位": 11,
      "LR2ID": "94429",
      "プレイヤー": "神谷奈緒",
      "スコア": "3433/3658(93.84%)",
      "PG": 1650,
      "GR": 133,
      "BPI": -15
    },
    {
      "順位": 12,
      "LR2ID": "180026",
      "プレイヤー": "ｷｱﾗ･ﾌｨﾘｰﾅ",
      "スコア": "2092/3658(57.18%)",
      "PG": 737,
      "GR": 618,
      "BPI": -15
    }
  ],
  "47": [
    {
      "順位": 1,
      "LR2ID": "63505",
      "プレイヤー": "生塩ノア",
      "スコア": "3284/3298(99.57%)",
      "PG": 1635,
      "GR": 14,
      "BPI": 64.9
    },
    {
      "順位": 2,
      "LR2ID": "105437",
      "プレイヤー": "comet*",
      "スコア": "3275/3298(99.3%)",
      "PG": 1626,
      "GR": 23,
      "BPI": 52.6
    },
    {
      "順位": 3,
      "LR2ID": "181781",
      "プレイヤー": "王雪",
      "スコア": "3273/3298(99.24%)",
      "PG": 1626,
      "GR": 21,
      "BPI": 50.47
    },
    {
      "順位": 4,
      "LR2ID": "184466",
      "プレイヤー": "なんこつ君",
      "スコア": "3271/3298(99.18%)",
      "PG": 1624,
      "GR": 23,
      "BPI": 48.48
    },
    {
      "順位": 5,
      "LR2ID": "158558",
      "プレイヤー": "ののか福丼",
      "スコア": "3254/3298(98.66%)",
      "PG": 1607,
      "GR": 40,
      "BPI": 35.31
    },
    {
      "順位": 6,
      "LR2ID": "61149",
      "プレイヤー": "卯月神楽",
      "スコア": "3253/3298(98.63%)",
      "PG": 1606,
      "GR": 41,
      "BPI": 34.68
    },
    {
      "順位": 7,
      "LR2ID": "116225",
      "プレイヤー": "各務チヒロ",
      "スコア": "3251/3298(98.57%)",
      "PG": 1605,
      "GR": 41,
      "BPI": 33.44
    },
    {
      "順位": 8,
      "LR2ID": "36363",
      "プレイヤー": "フリーナ",
      "スコア": "3244/3298(98.36%)",
      "PG": 1596,
      "GR": 52,
      "BPI": 29.42
    },
    {
      "順位": 9,
      "LR2ID": "140958",
      "プレイヤー": "浦和ハナコ",
      "スコア": "3243/3298(98.33%)",
      "PG": 1594,
      "GR": 55,
      "BPI": 28.88
    },
    {
      "順位": 10,
      "LR2ID": "187634",
      "プレイヤー": "大和赤驥",
      "スコア": "3226/3298(97.81%)",
      "PG": 1587,
      "GR": 52,
      "BPI": 20.59
    },
    {
      "順位": 11,
      "LR2ID": "94429",
      "プレイヤー": "神谷奈緒",
      "スコア": "3194/3298(96.84%)",
      "PG": 1553,
      "GR": 88,
      "BPI": 7.47
    }
  ]
}